Workbook

Sheet Factors
A1: Factor | B1: SweFor name | C1: Unit | D1: Ela-sticity | E1: Commodity type | F1: Extrac-tion Rate | G1: MinTrpVol | H1: TrpFactors | I1: SoilCtype | J1: C per Unit | K1: DF product | L1: DF finish | M1: DF half-life | N1: Initial (tC)
A2: Pine saw timber | B2: PinTim | C2: m3fub | D2: 0 | E2: L | F2: 0.98 | G2: 20 | H2: Y | I2: C
A3: Pine pulpwood | B3: PinPuw | C3: m3fub | D3: 0 | E3: L | F3: 0.92 | G3: 0 | H3: Y | I3: C
A4: Spruce saw timber | B4: SprTim | C4: m3fub | D4: 0 | E4: L | F4: 0.98 | G4: 20 | H4: Y | I4: C
A5: Spruce pulpwood | B5: SprPuw | C5: m3fub | D5: 0 | E5: L | F5: 0.92 | G5: 0 | H5: Y | I5: C
A6: Birch saw timber | B6: BerTim | C6: m3fub | D6: 0 | E6: L | F6: 0.98 | G6: 20 | H6: Y | I6: C
A7: Deciduous pulpwood | B7: Decids | C7: m3fub | D7: 0 | E7: L | F7: 0.88 | G7: 0 | H7: Y | I7: C
A8: Sawdust | B8: Sawdst | C8: m3fub | D8: 0 | E8: B | F8: 0 | G8: 0 | H8: Y
A9: Chips | B9: Chips_ | C9: m3fub | D9: 0 | E9: B | F9: 0 | G9: 0 | H9: Y
A10: Residues above gr. | B10: ResStm | C10: tonTS | D10: 0 | E10: R | F10: 0.65 | G10: 0 | H10: Y | I10: F
A11: Stump and roots | B11: ResRot | C11: tonTS | D11: 0 | E11: R | F11: 0 | G11: 0 | H11: Y | I11: C
A12: Forest fuel all kinds | B12: ForFue | C12: tonTS | D12: 0 | E12: R | F12: 0 | G12: 0 | H12: Y
A13: Timber all kinds | B13: AllTim | C13: m3fub | D13: 0 | E13: L | F13: 0 | G13: 0 | H13: Y
A14: Pulpwood all kinds | B14: AllPuw | C14: m3fub | D14: 0 | E14: L | F14: 0 | G14: 0 | H14: Y
A15: Sawn coniferous | B15: Sawnco | C15: m3sw | D15: -0.12254296 | E15: E | F15: 0 | G15: 0 | J15: =ConvFact!A2*ConvFact!A4 -> 0.23 | K15: 1.3 | L15: 0.4 | M15: 35 | N15: 115512122
A16: Sawn birch | B16: Sawnbe | C16: m3sw | D16: 0 | E16: P | F16: 0 | G16: 0 | J16: =ConvFact!A2*ConvFact!A4 -> 0.23 | K16: 1.3 | L16: 0.4 | M16: 35 | N16: 0
A17: Heat | B17: Heat__ | C17: MWh | D17: 0 | E17: F | F17: 0 | G17: 0 | J17: =ConvFact!A2*ConvFact!A4/ConvFact!A3 -> 0.10204082 | K17: 0.4 | L17: 0 | M17: 0 | N17: 0
A18: Electricity | B18: Electr | C18: MWh | D18: 0 | E18: P | F18: 0 | G18: 0 | J18: =ConvFact!A2*ConvFact!A4/ConvFact!A3 -> 0.10204082 | K18: 0.4 | L18: 0 | M18: 0 | N18: 0
A19: Biofuel | B19: BioFue | C19: MWh | D19: 0 | E19: D | F19: 0 | G19: 0 | J19: =ConvFact!A2*ConvFact!A4/ConvFact!A3 -> 0.10204082 | K19: 0.5 | L19: 0 | M19: 0 | N19: 0
A20: Pulp chem. process | B20: PuChem | C20: ton | D20: -0.5 | E20: E | F20: 0 | G20: 0 | J20: 0.45 | K20: 0 | L20: 0.4 | M20: 2 | N20: 37001679
A21: Pulp mech. process | B21: PuMech | C21: ton | D21: -0.5 | E21: E | F21: 0 | G21: 0 | J21: 0.388 | K21: 0 | L21: 0.4 | M21: 2 | N21: 0
A22: Dissolving pulp | B22: PuDiss | C22: ton | D22: -1.93 | E22: E | F22: 0 | G22: 0 | J22: 0.45 | K22: 2.8 | L22: 0.4 | M22: 2 | N22: 0
A23: Packaging | B23: PaChem | C23: ton | D23: -0.31123036 | E23: E | F23: 0 | G23: 0 | J23: =J20/ConvFact!A15 -> 0.40909091 | K23: 1 | L23: 0.4 | M23: 2 | N23: 0
A24: Other paper chem. | B24: OtChem | C24: ton | D24: -0.49445163 | E24: E | F24: 0 | G24: 0 | J24: =J20/ConvFact!A16 -> 0.34615385 | K24: 0 | L24: 0.4 | M24: 2 | N24: 0
A25: Other paper mech. | B25: OtMech | C25: ton | D25: -0.49445163 | E25: E | F25: 0 | G25: 0 | J25: =J21/ConvFact!A17 -> 0.29846154 | K25: 0 | L25: 0.4 | M25: 2 | N25: 0
A26: Newsprint | B26: NwMech | C26: ton | D26: -0.53473891 | E26: E | F26: 0 | G26: 0 | J26: =J21/ConvFact!A18 -> 0.35272727 | K26: 0 | L26: 0.4 | M26: 2 | N26: 0
A27: Particle board | B27: ParBoa | C27: m3fub | D27: -0.322 | E27: E | F27: 0 | G27: 0 | J27: 0.23 | K27: 1.3 | L27: 0.4 | M27: 35 | N27: 0
A29: Fibre board | B29: FibBoa | C29: m3fub | D29: -0.464 | E29: E | F29: 0 | G29: 0
A31: Sensitivity analysis coeff. | D31: 1 | E31: E | F31: Dermined by elasticity
E32: F | F32: The demanded quantititity should be met exactly and in propotion to initial capacity of each facility
E33: P | F33: Perfect elasticity
E34: D | F34: The demanded quantity should be met exactly
E35: L | F35: Logs
E36: R | F36: Residues and input to energy production
E37: B | F37: Byproducts

Sheet Processes
A1: Process | B1: Investment | C1: Fixed cost | D1: Depreciation period | E1: Output factor for costs | F1: NewCapacity
A2: Sawmpi | B2: 827.77291 | C2: 302.87324 | D2: 20 | E2: =Factors!B15 -> Sawnco | F2: 0
A3: Sawmsp | B3: 827.77291 | C3: 302.87324 | D3: 20 | E3: =E2 -> Sawnco | F3: 0
A4: Sawmbe | B4: 827.77291 | C4: 302.87324 | D4: 20 | E4: =E3 -> Sawnco | F4: 0
A5: Sawmal | B5: 827.77291 | C5: 302.87324 | D5: 20 | E5: =Factors!B16 -> Sawnbe | F5: 0
A6: Heatpl | B6: 1284.6312 | C6: 0 | D6: 20 | E6: =Factors!B17 -> Heat__ | F6: 0
A7: CHPpl_ | B7: 128.46312 | C7: 0 | D7: 20 | E7: Electr | F7: 0
A8: FTDpl_ | B8: 5087.1906 | C8: 0 | D8: 20 | E8: BioFue | F8: 0
A9: PuChem | B9: 16762.5 | C9: 650 | D9: 20 | E9: PuChem | F9: 0
A10: PuCTMP | B10: 14731.034 | C10: 736.55172 | D10: 20 | E10: PuMech | F10: 0
A11: PuMech | B11: 6444.8276 | C11: 736.55172 | D11: 20 | E11: PuMech | F11: 0
A12: PuDiss | B12: 16762.5 | C12: 650 | D12: 20 | E12: PuDiss | F12: 0
A13: PaChem | B13: 4751.0135 | C13: 250 | D13: 20 | E13: PaChem | F13: 0
A14: OtChem | B14: 4751.0135 | C14: 250 | D14: 20 | E14: OtChem | F14: 0
A15: OtMech | B15: 3068.9655 | C15: 153.44828 | D15: 20 | E15: OtMech | F15: 0
A16: NwMech | B16: 3068.9655 | C16: 153.44828 | D16: 20 | E16: NwMech | F16: 0
A17: PuBCCS | B17: 1 | C17: 1 | D17: 20 | E17: PuChem | F17: 0
A18: PaBCCS | B18: 1 | C18: 1 | D18: 20 | E18: PaChem | F18: 0
... A28: FibBoa | B28: 791 | C28: 264 | D28: 20 | E28: FibBoa | F28: 20

Sheet IO
A1: Column1 | B1: Column2 | C1: Column3 | D1: Column32 | E1: Column33 | F1: Column4 | G1: 1 | H1: 2 | I1: 3 | J1: 4 | K1: 5 | L1: 6 | M1: 7 | N1: 8 | O1: 9 | P1: 10 | Q1: 11 | R1: 12 | S1: 13 | T1: 14 | U1: 15 | V1: 16 | W1: 17 | X1: 18 | Y1: 19 | Z1: 20 | AA1: 21 | AB1: 22 | AC1: 23 | AD1: 24 | AE1: 25 | AF1: 252 | AG1: 253 | AH1: 254 | AI1: 255 | AJ1: 256 | AK1: 257 | AL1: Column5 | AM1: 27 | AN1: 28 | AO1: 29 | AP1: 30 | AQ1: 31 | AR1: 32 | AS1: 33 | AT1: 34 | AU1: 35
D2: ProcessCostPerInputUnit | E2: FixedMix | G2: MWhperTonDM | H2: TonDMperM3fub | I2: HeatPlantEfficiency | J2: CHPPlantEfficiency | K2: FTDPlantEfficiency | L2: M3fubSawdustPerM3fub | M2: M3fubChipsM3fub | N2: M3svPerM3fub | O2: TonSulphateSulphitePulpPerM3fub | P2: TonDissolvingPulpPerM3fub | Q2: TonMechanicalPulpPerM3fub | R2: TonHalfChemicalPulpPerM3fub | S2: TonPaChemPerTonPu | T2: TonOtChemPerTonPu | U2: TonOtMechPerTonPu | V2: TonNwMechPerTonPu | W2: MWhPerTonPuChem | X2: MWhPerTonPuCTMP | Y2: MWhPerTonPuMech | Z2: MWhPerTonPuDiss | AA2: MWhPerTonPpChem | AB2: MWhPerTonPuBCCS | AC2: MWhPerTonPpBCCS | AD2: MWhPerMWhBiofuel | AE2: DefaultCF | AF2: M3fubParBoaPerM3fub | AG2: MWhperM3fubParBoa | AH2: M3fubPaBoaPerM3fubSprPuw | AI2: M3fubPaBoaPerM3fubDecids | AJ2: M3fubPaBoaPerM3fubPinPuw | AK2: M3fubPaBoaPerM3fubSawdust
A3: Process | B3: Input | C3: Output | D3: SEK | E3: share | F3: IO | G3: 4.9 | H3: 0.46 | I3: 0.95 | J3: 1 | K3: 0.53 | L3: =[1]SawMill!$K$19 -> 0.17797461 | M3: =[1]SawMill!$K$18 -> 0.2545616 | N3: =[1]SawMill!$K$20 -> 0.45861152 | O3: 0.20833333 | P3: 0.20833333 | Q3: 0.41666667 | R3: 0.43478261 | S3: 1.1 | T3: 1.3 | U3: 1.3 | V3: 1.1 | W3: 0.036272879 | X3: -2.338843 | Y3: -1.7595745 | Z3: -0.69452055 | AA3: -0.561191 | AB3: 0.18372712 | AC3: -0.44 | AD3: -0.021 | AE3: 1 | AF3: 0.67 | AG3: -0.16405841
A4: Sawmpi | B4: PinTim | C4: Sawdst | D4: 0 | E4: 0 | F4: =PRODUCT(Table73[[#This Row],[1]:[25]]) -> 0.17797461 | L4: =L$3 -> 0.17797461
A5: Sawmpi | B5: PinTim | C5: Chips_ | D5: 0 | E5: 0 | F5: =PRODUCT(Table73[[#This Row],[1]:[25]]) -> 0.2545616 | M5: =M$3 -> 0.2545616
A6: Sawmpi | B6: PinTim | C6: Sawnco | D6: =[1]SawMill!$C$2*Table73[[#This Row],[Column4]] -> 141.61407 | E6: 0 | F6: =PRODUCT(Table73[[#This Row],[1]:[25]]) -> 0.45861152 | N6: =N$3 -> 0.45861152
A7: Sawmal | B7: PinTim | C7: Sawdst | D7: 0 | E7: 0 | F7: =PRODUCT(Table73[[#This Row],[1]:[25]]) -> 0.17797461 | L7: =L$3 -> 0.17797461
A8: Sawmal | B8: PinTim | C8: Chips_ | D8: 0 | E8: 0 | F8: =PRODUCT(Table73[[#This Row],[1]:[25]]) -> 0.2545616 | M8: =M$3 -> 0.2545616
A9: Sawmal | B9: PinTim | C9: Sawnco | D9: =[1]SawMill!$C$2*Table73[[#This Row],[Column4]] -> 141.61407 | E9: 0 | F9: =PRODUCT(Table73[[#This Row],[1]:[25]]) -> 0.45861152 | N9: =N$3 -> 0.45861152
A10: Sawmsp | B10: SprTim | C10: Sawdst | D10: 0 | E10: 0 | F10: =PRODUCT(Table73[[#This Row],[1]:[25]]) -> 0.17797461 | L10: =L$3 -> 0.17797461
A11: Sawmsp | B11: SprTim | C11: Chips_ | D11: 0 | E11: 0 | F11: =PRODUCT(Table73[[#This Row],[1]:[25]]) -> 0.2545616 | M11: =M$3 -> 0.2545616
A12: Sawmsp | B12: SprTim | C12: Sawnco | D12: =[1]SawMill!$C$2*Table73[[#This Row],[Column4]] -> 141.61407 | E12: 0 | F12: =PRODUCT(Table73[[#This Row],[1]:[25]]) -> 0.45861152 | N12: =N$3 -> 0.45861152
A13: Sawmal | B13: SprTim | C13: Sawdst | D13: 0 | E13: 0 | F13: =PRODUCT(Table73[[#This Row],[1]:[25]]) -> 0.17797461 | L13: =L$3 -> 0.17797461
A14: Sawmal | B14: SprTim | C14: Chips_ | D14: 0 | E14: 0 | F14: =PRODUCT(Table73[[#This Row],[1]:[25]]) -> 0.2545616 | M14: =M$3 -> 0.2545616
A15: Sawmal | B15: SprTim | C15: Sawnco | D15: =[1]SawMill!$C$2*Table73[[#This Row],[Column4]] -> 141.61407 | E15: 0 | F15: =PRODUCT(Table73[[#This Row],[1]:[25]]) -> 0.45861152 | N15: =N$3 -> 0.45861152
A16: Sawmbe | B16: BerTim | C16: Sawdst | D16: 0 | E16: 0 | F16: =PRODUCT(Table73[[#This Row],[1]:[25]]) -> 0.17797461 | L16: =L$3 -> 0.17797461
A17: Sawmbe | B17: BerTim | C17: Chips_ | D17: 0 | E17: 0 | F17: =PRODUCT(Table73[[#This Row],[1]:[25]]) -> 0.2545616 | M17: =M$3 -> 0.2545616
A18: Sawmbe | B18: BerTim | C18: Sawnbe | D18: =[1]SawMill!$C$2*Table73[[#This Row],[Column4]] -> 141.61407 | E18: 0 | F18: =PRODUCT(Table73[[#This Row],[1]:[25]]) -> 0.45861152 | N18: =N$3 -> 0.45861152
A19: TerFTD | B19: PinPuw | C19: ForFue | D19: 91 | E19: 0 | F19: =PRODUCT(Table73[[#This Row],[1]:[25]]) -> 0.46 | H19: =H$3 -> 0.46 | AL19: TerFTD | AM19: PinPuw | AN19: ForFue | AO19: 91 | AP19: 0.46 | AQ19: TerFTD | AR19: PinPuw | AS19: ForFue | AT19: 91 | AU19: 0.46
A20: TerFTD | B20: SprPuw | C20: ForFue | D20: 91 | E20: 0 | F20: =PRODUCT(Table73[[#This Row],[1]:[25]]) -> 0.46 | H20: =H$3 -> 0.46 | AL20: TerFTD | AM20: SprPuw | AN20: ForFue | AO20: 91 | AP20: 0.46 | AQ20: TerFTD | AR20: SprPuw | AS20: ForFue | AT20: 91 | AU20: 0.46
A21: TerFTD | B21: Decids | C21: ForFue | D21: 91 | E21: 0 | F21: =PRODUCT(Table73[[#This Row],[1]:[25]]) -> 0.46 | H21: =H$3 -> 0.46 | AL21: TerFTD | AM21: Decids | AN21: ForFue | AO21: 91 | AP21: 0.46 | AQ21: TerFTD | AR21: Decids | AS21: ForFue | AT21: 91 | AU21: 0.46
A22: TerFTD | B22: ResStm | C22: ForFue | D22: 149.6 | E22: 0 | F22: =PRODUCT(Table73[[#This Row],[1]:[25]]) -> 1 | AE22: =AE$3 -> 1 | AL22: TerFTD | AM22: ResStm | AN22: ForFue | AO22: 149.6 | AP22: 1 | AQ22: TerFTD | AR22: ResStm | AS22: ForFue | AT22: 149.6 | AU22: 1
A23: TerFTD | B23: ResRot | C23: ForFue | D23: 166.1 | E23: 0 | F23: =PRODUCT(Table73[[#This Row],[1]:[25]]) -> 1 | AE23: =AE$3 -> 1 | AL23: TerFTD | AM23: ResRot | AN23: ForFue | AO23: 166.1 | AP23: 1 | AQ23: TerFTD | AR23: ResRot | AS23: ForFue | AT23: 166.1 | AU23: 1
A24: TerFTD | B24: Chips_ | C24: ForFue | D24: 0 | E24: 0 | F24: =PRODUCT(Table73[[#This Row],[1]:[25]]) -> 0.46 | H24: =H$3 -> 0.46 | AL24: TerFTD | AM24: Chips_ | AN24: ForFue | AO24: 0 | AP24: 0.46 | AQ24: TerFTD | AR24: Chips_ | AS24: ForFue | AT24: 0 | AU24: 0.46
A25: TerFTD | B25: Sawdst | C25: ForFue | D25: 0 | E25: 0 | F25: =PRODUCT(Table73[[#This Row],[1]:[25]]) -> 0.46 | H25: =H$3 -> 0.46 | AL25: TerFTD | AM25: Sawdst | AN25: ForFue | AO25: 0 | AP25: 0.46 | AQ25: TerFTD | AR25: Sawdst | AS25: ForFue | AT25: 0 | AU25: 0.46
A26: FTDpl_ | B26: ForFue | C26: BioFue | D26: 1624.8796 | E26: 0 | F26: =PRODUCT(Table73[[#This Row],[1]:[25]]) -> 2.597 | G26: =G$3 -> 4.9 | K26: =K$3 -> 0.53 | AL26: FTDpl_ | AM26: ForFue | AN26: BioFue | AO26: 1624.8796 | AP26: 2.597 | AQ26: FTDpl_ | AR26: ForFue | AS26: BioFue | AT26: 1624.8796 | AU26: 2.597
A27: TerHea | B27: PinPuw | C27: ForFue | D27: 91 | E27: 0 | F27: =PRODUCT(Table73[[#This Row],[1]:[25]]) -> 0.46 | H27: =H$3 -> 0.46 | AL27: TerHea | AM27: PinPuw | AN27: ForFue | AO27: 91 | AP27: 0.46 | AQ27: Heatpl | AR27: PinPuw | AS27: Heat__ | AT27: 450.7384 | AU27: 2.254
A28: TerHea | B28: SprPuw | C28: ForFue | D28: 91 | E28: 0 | F28: =PRODUCT(Table73[[#This Row],[1]:[25]]) -> 0.46 | H28: =H$3 -> 0.46 | AL28: TerHea | AM28: SprPuw | AN28: ForFue | AO28: 91 | AP28: 0.46 | AQ28: Heatpl | AR28: SprPuw | AS28: Heat__ | AT28: 450.7384 | AU28: 2.254
A29: TerHea | B29: Decids | C29: ForFue | D29: 91 | E29: 0 | F29: =PRODUCT(Table73[[#This Row],[1]:[25]]) -> 0.46 | H29: =H$3 -> 0.46 | AL29: TerHea | AM29: Decids | AN29: ForFue | AO29: 91 | AP29: 0.46 | AQ29: Heatpl | AR29: Decids | AS29: Heat__ | AT29: 450.7384 | AU29: 2.254
A30: TerHea | B30: ResStm | C30: ForFue | D30: 149.6 | E30: 0 | F30: =PRODUCT(Table73[[#This Row],[1]:[25]]) -> 1 | AE30: =AE$3 -> 1 | AL30: TerHea | AM30: ResStm | AN30: ForFue | AO30: 149.6 | AP30: 1 | AQ30: Heatpl | AR30: ResStm | AS30: Heat__ | AT30: 931.64 | AU30: 4.9
A31: TerHea | B31: ResRot | C31: ForFue | D31: 166.1 | E31: 0 | F31: =PRODUCT(Table73[[#This Row],[1]:[25]]) -> 1 | AE31: =AE$3 -> 1 | AL31: TerHea | AM31: ResRot | AN31: ForFue | AO31: 166.1 | AP31: 1 | AQ31: Heatpl | AR31: ResRot | AS31: Heat__ | AT31: 948.14 | AU31: 4.9
A32: TerHea | B32: Chips_ | C32: ForFue | D32: 0 | E32: 0 | F32: =PRODUCT(Table73[[#This Row],[1]:[25]]) -> 0.46 | H32: =H$3 -> 0.46 | AL32: TerHea | AM32: Chips_ | AN32: ForFue | AO32: 0 | AP32: 0.46 | AQ32: Heatpl | AR32: ForFue | AS32: Heat__ | AT32: 782.04 | AU32: 4.655
A33: TerHea | B33: Sawdst | C33: ForFue | D33: 0 | E33: 0 | F33: =PRODUCT(Table73[[#This Row],[1]:[25]]) -> 0.46 | H33: =H$3 -> 0.46 | AL33: TerHea | AM33: Sawdst | AN33: ForFue | AO33: 0 | AP33: 0.46 | AQ33: Heatpl | AR33: Chips_ | AS33: Heat__ | AT33: 359.7384 | AU33: 2.1413
A34: Heatpl | B34: ForFue | C34: Heat__ | D34: 782.04 | E34: 0 | F34: =PRODUCT(Table73[[#This Row],[1]:[25]]) -> 4.655 | G34: =G$3 -> 4.9 | I34: 0.95 | AL34: Heatpl | AM34: ForFue | AN34: Heat__ | AO34: 782.04 | AP34: 4.655 | AQ34: Heatpl | AR34: Sawdst | AS34: Heat__ | AT34: 359.7384 | AU34: 2.1413
A35: Heatpl | B35: Chips_ | C35: Heat__ | D35: 359.7384 | E35: 0 | F35: =PRODUCT(Table73[[#This Row],[1]:[25]]) -> 2.254 | G35: =G$3 -> 4.9 | H35: =H$3 -> 0.46 | AL35: Heatpl | AM35: Chips_ | AN35: Heat__ | AO35: 359.7384 | AP35: 2.1413 | AQ35: FTDpl_ | AR35: Chips_ | AS35: BioFue | AT35: 200.69616 | AU35: 1.19462
A36: Heatpl | B36: Sawdst | C36: Heat__ | D36: 359.7384 | E36: 0 | F36: =PRODUCT(Table73[[#This Row],[1]:[25]]) -> 2.254 | G36: =G$3 -> 4.9 | H36: =H$3 -> 0.46 | AL36: Heatpl | AM36: Sawdst | AN36: Heat__ | AO36: 359.7384 | AP36: 2.1413 | AQ36: FTDpl_ | AR36: Sawdst | AS36: BioFue | AT36: 200.69616 | AU36: 1.19462
A37: FTDpl_ | B37: Chips_ | C37: BioFue | D37: 200.69616 | E37: 0 | F37: =PRODUCT(Table73[[#This Row],[1]:[25]]) -> 1.19462 | G37: =G$3 -> 4.9 | H37: =H$3 -> 0.46 | K37: =K$3 -> 0.53 | AL37: FTDpl_ | AM37: Chips_ | AN37: BioFue | AO37: 200.69616 | AP37: 1.19462
A38: FTDpl_ | B38: Sawdst | C38: BioFue | D38: 200.69616 | E38: 0 | F38: =PRODUCT(Table73[[#This Row],[1]:[25]]) -> 1.19462 | G38: =G$3 -> 4.9 | H38: =H$3 -> 0.46 | K38: =K$3 -> 0.53 | AL38: FTDpl_ | AM38: Sawdst | AN38: BioFue | AO38: 200.69616 | AP38: 1.19462
A39: PuChem | B39: PinTim | C39: PuChem | D39: 179.16667 | E39: 0 | F39: =PRODUCT(Table73[[#This Row],[1]:[25]]) -> 0.20833333 | O39: =O$3 -> 0.20833333
A40: PuChem | B40: SprTim | C40: PuChem | D40: 179.16667 | E40: 0 | F40: =PRODUCT(Table73[[#This Row],[1]:[25]]) -> 0.20833333 | O40: =O$3 -> 0.20833333
A41: PuChem | B41: PinPuw | C41: PuChem | D41: 179.16667 | E41: 0 | F41: =PRODUCT(Table73[[#This Row],[1]:[25]]) -> 0.20833333 | O41: =O$3 -> 0.20833333
A42: PuChem | B42: SprPuw | C42: PuChem | D42: 179.16667 | E42: 0 | F42: =PRODUCT(Table73[[#This Row],[1]:[25]]) -> 0.20833333 | O42: =O$3 -> 0.20833333
A43: PuChem | B43: BerTim | C43: PuChem | D43: 179.16667 | E43: 0 | F43: =PRODUCT(Table73[[#This Row],[1]:[25]]) -> 0.20833333 | O43: =O$3 -> 0.20833333
A44: PuChem | B44: Decids | C44: PuChem | D44: 179.16667 | E44: 0 | F44: =PRODUCT(Table73[[#This Row],[1]:[25]]) -> 0.20833333 | O44: =O$3 -> 0.20833333
A45: PuChem | B45: Chips_ | C45: PuChem | D45: 179.16667 | E45: 0 | F45: =PRODUCT(Table73[[#This Row],[1]:[25]]) -> 0.20833333 | O45: =O$3 -> 0.20833333
A46: PuDiss | B46: PinTim | C46: PuDiss | D46: 179.16667 | E46: 0 | F46: =PRODUCT(Table73[[#This Row],[1]:[25]]) -> 0.20833333 | O46: =O$3 -> 0.20833333
A47: PuDiss | B47: SprTim | C47: PuDiss | D47: 179.16667 | E47: 0 | F47: =PRODUCT(Table73[[#This Row],[1]:[25]]) -> 0.20833333 | O47: =O$3 -> 0.20833333
A48: PuDiss | B48: PinPuw | C48: PuDiss | D48: 179.16667 | E48: 0 | F48: =PRODUCT(Table73[[#This Row],[1]:[25]]) -> 0.20833333 | O48: =O$3 -> 0.20833333
A49: PuDiss | B49: SprPuw | C49: PuDiss | D49: 179.16667 | E49: 0 | F49: =PRODUCT(Table73[[#This Row],[1]:[25]]) -> 0.20833333 | O49: =O$3 -> 0.20833333
A50: PuDiss | B50: BerTim | C50: PuDiss | D50: 179.16667 | E50: 0 | F50: =PRODUCT(Table73[[#This Row],[1]:[25]]) -> 0.20833333 | O50: =O$3 -> 0.20833333
... A52: PuDiss | B52: Chips_ | C52: PuDiss | D52: 179.16667 | E52: 0 | F52: =PRODUCT(Table73[[#This Row],[1]:[25]]) -> 0.20833333 | O52: =O$3 -> 0.20833333
A53: PuChem | B53: PinTim | C53: Electr | D53: 0 | E53: 0 | F53: =PRODUCT(Table73[[#This Row],[1]:[25]]) -> 0.0075568497 | O53: =O$3 -> 0.20833333 | W53: =W$3 -> 0.036272879
A54: PuChem | B54: SprTim | C54: Electr | D54: 0 | E54: 0 | F54: =PRODUCT(Table73[[#This Row],[1]:[25]]) -> 0.0075568497 | O54: =O$3 -> 0.20833333 | W54: =W$3 -> 0.036272879
A55: PuChem | B55: PinPuw | C55: Electr | D55: 0 | E55: 0 | F55: =PRODUCT(Table73[[#This Row],[1]:[25]]) -> 0.0075568497 | O55: =O$3 -> 0.20833333 | W55: =W$3 -> 0.036272879
A56: PuChem | B56: SprPuw | C56: Electr | D56: 0 | E56: 0 | F56: =PRODUCT(Table73[[#This Row],[1]:[25]]) -> 0.0075568497 | O56: =O$3 -> 0.20833333 | W56: =W$3 -> 0.036272879
A57: PuChem | B57: Decids | C57: Electr | D57: 0 | E57: 0 | F57: =PRODUCT(Table73[[#This Row],[1]:[25]]) -> 0.0075568497 | O57: =O$3 -> 0.20833333 | W57: =W$3 -> 0.036272879
A58: PuChem | B58: Chips_ | C58: Electr | D58: 0 | E58: 0 | F58: =PRODUCT(Table73[[#This Row],[1]:[25]]) -> 0.0075568497 | O58: =O$3 -> 0.20833333 | W58: =W$3 -> 0.036272879
A59: PuDiss | B59: PinTim | C59: Electr | D59: 0 | E59: 0 | F59: =PRODUCT(Table73[[#This Row],[1]:[25]]) -> -0.14469178 | P59: =P$3 -> 0.20833333 | Z59: =Z$3 -> -0.69452055
A60: PuDiss | B60: SprTim | C60: Electr | D60: 0 | E60: 0 | F60: =PRODUCT(Table73[[#This Row],[1]:[25]]) -> -0.14469178 | P60: =P$3 -> 0.20833333 | Z60: =Z$3 -> -0.69452055
A61: PuDiss | B61: PinPuw | C61: Electr | D61: 0 | E61: 0 | F61: =PRODUCT(Table73[[#This Row],[1]:[25]]) -> -0.14469178 | P61: =P$3 -> 0.20833333 | Z61: =Z$3 -> -0.69452055
A62: PuDiss | B62: SprPuw | C62: Electr | D62: 0 | E62: 0 | F62: =PRODUCT(Table73[[#This Row],[1]:[25]]) -> -0.14469178 | P62: =P$3 -> 0.20833333 | Z62: =Z$3 -> -0.69452055
A63: PuDiss | B63: Decids | C63: Electr | D63: 0 | E63: 0 | F63: =PRODUCT(Table73[[#This Row],[1]:[25]]) -> -0.14469178 | P63: =P$3 -> 0.20833333 | Z63: =Z$3 -> -0.69452055
A64: PuDiss | B64: Chips_ | C64: Electr | D64: 0 | E64: 0 | F64: =PRODUCT(Table73[[#This Row],[1]:[25]]) -> -0.14469178 | P64: =P$3 -> 0.20833333 | Z64: =Z$3 -> -0.69452055
A65: PuCTMP | B65: SprTim | C65: Electr | D65: 0 | E65: 0 | F65: =PRODUCT(Table73[[#This Row],[1]:[25]]) -> -1.0168883 | R65: =R$3 -> 0.43478261 | X65: =X$3 -> -2.338843
A66: PuCTMP | B66: SprPuw | C66: Electr | D66: 0 | E66: 0 | F66: =PRODUCT(Table73[[#This Row],[1]:[25]]) -> -1.0168883 | R66: =R$3 -> 0.43478261 | X66: =X$3 -> -2.338843
A67: PuCTMP | B67: SprTim | C67: PuMech | D67: 373.91304 | E67: 0 | F67: =PRODUCT(Table73[[#This Row],[1]:[25]]) -> 0.43478261 | R67: =R$3 -> 0.43478261
A68: PuCTMP | B68: SprPuw | C68: PuMech | D68: 373.91304 | E68: 0 | F68: =PRODUCT(Table73[[#This Row],[1]:[25]]) -> 0.43478261 | R68: =R$3 -> 0.43478261
A69: PuMech | B69: SprTim | C69: Electr | D69: 0 | E69: 0 | F69: =PRODUCT(Table73[[#This Row],[1]:[25]]) -> -0.73315603 | Q69: =Q$3 -> 0.41666667 | Y69: =Y$3 -> -1.7595745
A70: PuMech | B70: SprPuw | C70: Electr | D70: 0 | E70: 0 | F70: =PRODUCT(Table73[[#This Row],[1]:[25]]) -> -0.73315603 | Q70: =Q$3 -> 0.41666667 | Y70: =Y$3 -> -1.7595745
A71: PuMech | B71: SprTim | C71: PuMech | D71: 358.33333 | E71: 0 | F71: =PRODUCT(Table73[[#This Row],[1]:[25]]) -> 0.41666667 | Q71: =Q$3 -> 0.41666667
A72: PuMech | B72: SprPuw | C72: PuMech | D72: 358.33333 | E72: 0 | F72: =PRODUCT(Table73[[#This Row],[1]:[25]]) -> 0.41666667 | Q72: =Q$3 -> 0.41666667
A73: PaChem | B73: PuChem | C73: Electr | D73: 0 | E73: 0 | F73: =PRODUCT(Table73[[#This Row],[1]:[25]]) -> -0.6173101 | S73: =S$3 -> 1.1 | AA73: =AA$3 -> -0.561191
A74: PaChem | B74: PuChem | C74: PaChem | D74: 198 | E74: 0 | F74: =PRODUCT(Table73[[#This Row],[1]:[25]]) -> 1.1 | S74: =S$3 -> 1.1
A75: OtChem | B75: PuChem | C75: Electr | D75: 0 | E75: 0 | F75: =PRODUCT(Table73[[#This Row],[1]:[25]]) -> -0.7295483 | T75: =T$3 -> 1.3 | AA75: =AA$3 -> -0.561191
A76: OtChem | B76: PuChem | C76: OtChem | D76: 234 | E76: 0 | F76: =PRODUCT(Table73[[#This Row],[1]:[25]]) -> 1.3 | T76: =T$3 -> 1.3
A77: OtMech | B77: PuMech | C77: OtMech | D77: 234 | E77: 0 | F77: =PRODUCT(Table73[[#This Row],[1]:[25]]) -> 1.3 | U77: =U$3 -> 1.3
A78: NwMech | B78: PuMech | C78: NwMech | D78: 198 | E78: 0 | F78: =PRODUCT(Table73[[#This Row],[1]:[25]]) -> 1.1 | V78: =V$3 -> 1.1
A79: PuBCCS | B79: PuChem | C79: Electr | D79: 0 | E79: 0 | F79: =PRODUCT(Table73[[#This Row],[1]:[25]]) -> 0
A80: PuBCCS | B80: PuChem | C80: PuChem | D80: 0 | E80: 0 | F80: =PRODUCT(Table73[[#This Row],[1]:[25]]) -> 0
A81: PaBCCS | B81: PaChem | C81: Electr | D81: 0 | E81: 0 | F81: =PRODUCT(Table73[[#This Row],[1]:[25]]) -> 0
A82: PaBCCS | B82: PaChem | C82: PaChem | D82: 0 | E82: 0 | F82: =PRODUCT(Table73[[#This Row],[1]:[25]]) -> 0
A83: OtBCCS | B83: OtChem | C83: Electr | D83: 0 | E83: 0 | F83: =PRODUCT(Table73[[#This Row],[1]:[25]]) -> 0
A84: OtBCCS | B84: OtChem | C84: OtChem | D84: 0 | E84: 0 | F84: =PRODUCT(Table73[[#This Row],[1]:[25]]) -> 0
A85: ParBoa | B85: Sawdst | C85: ParBoa | D85: =529*Table73[[#This Row],[Column4]] -> 354.43 | E85: 0.75 | F85: =PRODUCT(Table73[[#This Row],[1]:[252]]) -> 0.67 | AF85: =AF$3 -> 0.67
A86: TerPal | B86: SprPuw | C86: AllPuw | D86: 0 | E86: 0 | F86: =PRODUCT(Table73[[#This Row],[1]:[252]]) -> 0.67 | AF86: =AF$3 -> 0.67
A87: TerPal | B87: Decids | C87: AllPuw | D87: 0 | E87: 0 | F87: =PRODUCT(Table73[[#This Row],[1]:[252]]) -> 0.67 | AF87: =AF$3 -> 0.67
A88: TerPal | B88: PinPuw | C88: AllPuw | D88: 0 | E88: 0 | F88: =PRODUCT(Table73[[#This Row],[1]:[252]]) -> 0.67 | AF88: =AF$3 -> 0.67
A89: ParBoa | B89: AllPuw | C89: Parboa | D89: =529*Table73[[#This Row],[Column4]] -> 354.43 | E89: 0.25 | F89: =PRODUCT(Table73[[#This Row],[1]:[252]]) -> 0.67 | AF89: =AF$3 -> 0.67
A90: ParBoa | B90: Sawdst | C90: Electr | D90: 0 | E90: 0 | F90: =PRODUCT(Table73[[#This Row],[1]:[253]]) -> -0.10991914 | AF90: =AF$3 -> 0.67 | AG90: =AG$3 -> -0.16405841
A91: ParBoa | B91: AllPuw | C91: Electr | D91: 0 | E91: 0 | F91: =PRODUCT(Table73[[#This Row],[1]:[253]]) -> -0.10991914 | AF91: =AF$3 -> 0.67 | AG91: =AG$3 -> -0.16405841
A93: PuChem | B93: PinTim | C93: Electr | F93: =PRODUCT(Table73[[#This Row],[1]:[25]]) -> #VALUE! | O93: =O$3 -> 0.20833333 | W93: =W$3 -> 0.036272879
A94: PuChem | B94: SprTim | C94: Electr | F94: =PRODUCT(Table73[[#This Row],[1]:[25]]) -> #VALUE! | O94: =O$3 -> 0.20833333 | W94: =W$3 -> 0.036272879
A95: PuChem | B95: PinPuw | C95: Electr | F95: =PRODUCT(Table73[[#This Row],[1]:[25]]) -> #VALUE! | O95: =O$3 -> 0.20833333 | W95: =W$3 -> 0.036272879
A96: PuChem | B96: SprPuw | C96: Electr | F96: =PRODUCT(Table73[[#This Row],[1]:[25]]) -> #VALUE! | O96: =O$3 -> 0.20833333 | W96: =W$3 -> 0.036272879
A97: PuChem | B97: Decids | C97: Electr | F97: =PRODUCT(Table73[[#This Row],[1]:[25]]) -> #VALUE! | O97: =O$3 -> 0.20833333 | W97: =W$3 -> 0.036272879
A98: PuChem | B98: Chips_ | C98: Electr | F98: =PRODUCT(Table73[[#This Row],[1]:[25]]) -> #VALUE! | O98: =O$3 -> 0.20833333 | W98: =W$3 -> 0.036272879
A99: PuChem | B99: PinTim | C99: PuChem | F99: =PRODUCT(Table73[[#This Row],[1]:[25]]) -> #VALUE! | O99: =O$3 -> 0.20833333
A100: PuChem | B100: SprTim | C100: PuChem | F100: =PRODUCT(Table73[[#This Row],[1]:[25]]) -> #VALUE! | O100: =O$3 -> 0.20833333
A101: PuChem | B101: PinPuw | C101: PuChem | F101: =PRODUCT(Table73[[#This Row],[1]:[25]]) -> #VALUE! | O101: =O$3 -> 0.20833333
A102: PuChem | B102: SprPuw | C102: PuChem | F102: =PRODUCT(Table73[[#This Row],[1]:[25]]) -> #VALUE! | O102: =O$3 -> 0.20833333
...

Sheet Trp
A1: Transports | E1: Fixed | F1: Variable | G1: Options
A2: Factor --> Process | B2: =Factors!B1 -> SweFor name | C2: =Factors!C1 -> Unit | D2: Max trp | E2: Fixed trp cost | F2: Variable trp cost | G2: {=TRANSPOSE(Processes!A2:A28)} -> Sawmpi | H2: Sawmsp | I2: Sawmbe | J2: Sawmal | K2: Heatpl | L2: CHPpl_ | M2: FTDpl_ | N2: PuChem | O2: PuCTMP | P2: PuMech | Q2: PuDiss | R2: PaChem | S2: OtChem | T2: OtMech | U2: NwMech | V2: PuBCCS | W2: PaBCCS | X2: OtBCCS | Y2: TerFTD | Z2: TerTsp | AA2: TerTal | AB2: TerPsp | AC2: TerPal | AD2: TerHea | AE2: ParBoa
A3: =Factors!A2 -> Pine saw timber | B3: =Factors!B2 -> PinTim | C3: =Factors!C2 -> m3fub | D3: 300 | E3: =36*ConvFact!$A$2 -> 16.56 | F3: =1.62*ConvFact!$A$2 -> 0.7452 | G3: 2 | H3: 0 | I3: 0 | J3: 2 | K3: 0 | L3: 0 | M3: 0 | N3: 2 | O3: 0 | P3: 0 | Q3: 2 | R3: 0 | S3: 0 | T3: 0 | U3: 0 | V3: 0 | W3: 0 | X3: 0 | Y3: 0 | Z3: 0 | AA3: 0 | AB3: 0 | AC3: 0 | AD3: 0 | AE3: 0
A4: =Factors!A3 -> Pine pulpwood | B4: =Factors!B3 -> PinPuw | C4: =Factors!C3 -> m3fub | D4: 300 | E4: =36*ConvFact!$A$2 -> 16.56 | F4: =1.62*ConvFact!$A$2 -> 0.7452 | G4: 0 | H4: 0 | I4: 0 | J4: 0 | K4: 0 | L4: 0 | M4: 0 | N4: 2 | O4: 0 | P4: 0 | Q4: 2 | R4: 0 | S4: 0 | T4: 0 | U4: 0 | V4: 0 | W4: 0 | X4: 0 | Y4: 0 | Z4: 0 | AA4: 0 | AB4: 0 | AC4: 2 | AD4: 2 | AE4: 0
A5: =Factors!A4 -> Spruce saw timber | B5: =Factors!B4 -> SprTim | C5: =Factors!C4 -> m3fub | D5: 300 | E5: =36*ConvFact!$A$2 -> 16.56 | F5: =1.62*ConvFact!$A$2 -> 0.7452 | G5: 0 | H5: 2 | I5: 0 | J5: 2 | K5: 0 | L5: 0 | M5: 0 | N5: 2 | O5: 2 | P5: 2 | Q5: 2 | R5: 0 | S5: 0 | T5: 0 | U5: 0 | V5: 0 | W5: 0 | X5: 0 | Y5: 0 | Z5: 0 | AA5: 0 | AB5: 0 | AC5: 0 | AD5: 0 | AE5: 0
A6: =Factors!A5 -> Spruce pulpwood | B6: =Factors!B5 -> SprPuw | C6: =Factors!C5 -> m3fub | D6: 300 | E6: =36*ConvFact!$A$2 -> 16.56 | F6: =1.62*ConvFact!$A$2 -> 0.7452 | G6: 0 | H6: 0 | I6: 0 | J6: 0 | K6: 0 | L6: 0 | M6: 0 | N6: 2 | O6: 2 | P6: 2 | Q6: 2 | R6: 0 | S6: 0 | T6: 0 | U6: 0 | V6: 0 | W6: 0 | X6: 0 | Y6: 0 | Z6: 0 | AA6: 0 | AB6: 0 | AC6: 2 | AD6: 2 | AE6: 0
A7: =Factors!A6 -> Birch saw timber | B7: =Factors!B6 -> BerTim | C7: =Factors!C6 -> m3fub | D7: 301 | E7: =36*ConvFact!$A$2 -> 16.56 | F7: =1.62*ConvFact!$A$2 -> 0.7452 | G7: 0 | H7: 0 | I7: 0 | J7: 0 | K7: 0 | L7: 0 | M7: 0 | N7: 2 | O7: 0 | P7: 0 | Q7: 2 | R7: 0 | S7: 0 | T7: 0 | U7: 0 | V7: 0 | W7: 0 | X7: 0 | Y7: 0 | Z7: 0 | AA7: 0 | AB7: 0 | AC7: 0 | AD7: 0 | AE7: 0
A8: =Factors!A7 -> Deciduous pulpwood | B8: =Factors!B7 -> Decids | C8: =Factors!C7 -> m3fub | D8: 300 | E8: =36*ConvFact!$A$2 -> 16.56 | F8: =1.62*ConvFact!$A$2 -> 0.7452 | G8: 0 | H8: 0 | I8: 0 | J8: 0 | K8: 0 | L8: 0 | M8: 0 | N8: 2 | O8: 0 | P8: 0 | Q8: 2 | R8: 0 | S8: 0 | T8: 0 | U8: 0 | V8: 0 | W8: 0 | X8: 0 | Y8: 0 | Z8: 0 | AA8: 0 | AB8: 0 | AC8: 2 | AD8: 2 | AE8: 0
A9: =Factors!A8 -> Sawdust | B9: =Factors!B8 -> Sawdst | C9: =Factors!C8 -> m3fub | D9: 300 | E9: =36*ConvFact!$A$2 -> 16.56 | F9: =1.62*ConvFact!$A$2 -> 0.7452 | G9: 0 | H9: 0 | I9: 0 | J9: 0 | K9: 0 | L9: 0 | M9: 0 | N9: 0 | O9: 0 | P9: 0 | Q9: 0 | R9: 0 | S9: 0 | T9: 0 | U9: 0 | V9: 0 | W9: 0 | X9: 0 | Y9: 0 | Z9: 0 | AA9: 0 | AB9: 0 | AC9: 0 | AD9: 30 | AE9: 2
A10: =Factors!A9 -> Chips | B10: =Factors!B9 -> Chips_ | C10: =Factors!C9 -> m3fub | D10: 300 | E10: =36*ConvFact!$A$2 -> 16.56 | F10: =1.62*ConvFact!$A$2 -> 0.7452 | G10: 0 | H10: 0 | I10: 0 | J10: 0 | K10: 0 | L10: 0 | M10: 0 | N10: 2 | O10: 0 | P10: 0 | Q10: 2 | R10: 0 | S10: 0 | T10: 0 | U10: 0 | V10: 0 | W10: 0 | X10: 0 | Y10: 0 | Z10: 0 | AA10: 0 | AB10: 0 | AC10: 0 | AD10: 30 | AE10: 0
A11: =Factors!A10 -> Residues above gr. | B11: =Factors!B10 -> ResStm | C11: =Factors!C10 -> tonTS | D11: 300 | E11: 54 | F11: 1.9 | G11: 0 | H11: 0 | I11: 0 | J11: 0 | K11: 0 | L11: 0 | M11: 0 | N11: 0 | O11: 0 | P11: 0 | Q11: 0 | R11: 0 | S11: 0 | T11: 0 | U11: 0 | V11: 0 | W11: 0 | X11: 0 | Y11: 0 | Z11: 0 | AA11: 0 | AB11: 0 | AC11: 0 | AD11: 30 | AE11: 0
A12: =Factors!A11 -> Stump and roots | B12: =Factors!B11 -> ResRot | C12: =Factors!C11 -> tonTS | D12: 300 | E12: 54 | F12: 1.9 | G12: 0 | H12: 0 | I12: 0 | J12: 0 | K12: 0 | L12: 0 | M12: 0 | N12: 0 | O12: 0 | P12: 0 | Q12: 0 | R12: 0 | S12: 0 | T12: 0 | U12: 0 | V12: 0 | W12: 0 | X12: 0 | Y12: 0 | Z12: 0 | AA12: 0 | AB12: 0 | AC12: 0 | AD12: 0 | AE12: 0
A13: =Factors!A12 -> Forest fuel all kinds | B13: =Factors!B12 -> ForFue | C13: =Factors!C12 -> tonTS | D13: 300 | E13: =E11/10 -> 5.4 | F13: =F11 -> 1.9 | G13: 0 | H13: 0 | I13: 0 | J13: 0 | K13: 0 | L13: 0 | M13: 0 | N13: 0 | O13: 0 | P13: 0 | Q13: 0 | R13: 0 | S13: 0 | T13: 0 | U13: 0 | V13: 0 | W13: 0 | X13: 0 | Y13: 0 | Z13: 0 | AA13: 0 | AB13: 0 | AC13: 0 | AD13: 0 | AE13: 0
A14: =Factors!A13 -> Timber all kinds | B14: =Factors!B13 -> AllTim | C14: =Factors!C13 -> m3fub | D14: 300 | E14: =E3/10 -> 1.656 | F14: =1.62*ConvFact!$A$2 -> 0.7452 | G14: 0 | H14: 0 | I14: 0 | J14: 0 | K14: 0 | L14: 0 | M14: 0 | N14: 0 | O14: 0 | P14: 0 | Q14: 0 | R14: 0 | S14: 0 | T14: 0 | U14: 0 | V14: 0 | W14: 0 | X14: 0 | Y14: 0 | Z14: 0 | AA14: 0 | AB14: 0 | AC14: 0 | AD14: 0 | AE14: 0
A15: =Factors!A14 -> Pulpwood all kinds | B15: =Factors!B14 -> AllPuw | C15: =Factors!C14 -> m3fub | D15: 300 | E15: =E3/10 -> 1.656 | F15: =1.62*ConvFact!$A$2 -> 0.7452 | G15: 0 | H15: 0 | I15: 0 | J15: 0 | K15: 0 | L15: 0 | M15: 0 | N15: 0 | O15: 0 | P15: 0 | Q15: 0 | R15: 0 | S15: 0 | T15: 0 | U15: 0 | V15: 0 | W15: 0 | X15: 0 | Y15: 0 | Z15: 0 | AA15: 0 | AB15: 0 | AC15: 0 | AD15: 0 | AE15: 0
G17: 2 | H17: 0 | I17: 0 | J17: 2 | K17: 0 | L17: 0 | M17: 0 | N17: 2 | O17: 0 | P17: 0 | Q17: 2 | R17: 0 | S17: 0 | T17: 0 | U17: 0 | V17: 0 | W17: 0 | X17: 0 | Y17: 0 | Z17: 0 | AA17: 0 | AB17: 0 | AC17: 0 | AD17: 0
G18: 0 | H18: 0 | I18: 0 | J18: 0 | K18: 0 | L18: 0 | M18: 0 | N18: 2 | O18: 0 | P18: 0 | Q18: 2 | R18: 0 | S18: 0 | T18: 0 | U18: 0 | V18: 0 | W18: 0 | X18: 0 | Y18: 0 | Z18: 0 | AA18: 0 | AB18: 0 | AC18: 0 | AD18: 2
G19: 0 | H19: 2 | I19: 0 | J19: 2 | K19: 0 | L19: 0 | M19: 0 | N19: 2 | O19: 2 | P19: 2 | Q19: 2 | R19: 0 | S19: 0 | T19: 0 | U19: 0 | V19: 0 | W19: 0 | X19: 0 | Y19: 0 | Z19: 0 | AA19: 0 | AB19: 0 | AC19: 0 | AD19: 0
G20: 0 | H20: 0 | I20: 0 | J20: 0 | K20: 0 | L20: 0 | M20: 0 | N20: 2 | O20: 2 | P20: 2 | Q20: 2 | R20: 0 | S20: 0 | T20: 0 | U20: 0 | V20: 0 | W20: 0 | X20: 0 | Y20: 0 | Z20: 0 | AA20: 0 | AB20: 0 | AC20: 0 | AD20: 2
G21: 0 | H21: 0 | I21: 0 | J21: 0 | K21: 0 | L21: 0 | M21: 0 | N21: 2 | O21: 0 | P21: 0 | Q21: 2 | R21: 0 | S21: 0 | T21: 0 | U21: 0 | V21: 0 | W21: 0 | X21: 0 | Y21: 0 | Z21: 0 | AA21: 0 | AB21: 0 | AC21: 0 | AD21: 0
G22: 0 | H22: 0 | I22: 0 | J22: 0 | K22: 0 | L22: 0 | M22: 0 | N22: 2 | O22: 0 | P22: 0 | Q22: 2 | R22: 0 | S22: 0 | T22: 0 | U22: 0 | V22: 0 | W22: 0 | X22: 0 | Y22: 0 | Z22: 0 | AA22: 0 | AB22: 0 | AC22: 0 | AD22: 2
G23: 0 | H23: 0 | I23: 0 | J23: 0 | K23: 0 | L23: 0 | M23: 0 | N23: 0 | O23: 0 | P23: 0 | Q23: 0 | R23: 0 | S23: 0 | T23: 0 | U23: 0 | V23: 0 | W23: 0 | X23: 0 | Y23: 0 | Z23: 0 | AA23: 0 | AB23: 0 | AC23: 0 | AD23: 30
G24: 0 | H24: 0 | I24: 0 | J24: 0 | K24: 0 | L24: 0 | M24: 0 | N24: 2 | O24: 0 | P24: 0 | Q24: 2 | R24: 0 | S24: 0 | T24: 0 | U24: 0 | V24: 0 | W24: 0 | X24: 0 | Y24: 0 | Z24: 0 | AA24: 0 | AB24: 0 | AC24: 0 | AD24: 30
G25: 0 | H25: 0 | I25: 0 | J25: 0 | K25: 0 | L25: 0 | M25: 0 | N25: 0 | O25: 0 | P25: 0 | Q25: 0 | R25: 0 | S25: 0 | T25: 0 | U25: 0 | V25: 0 | W25: 0 | X25: 0 | Y25: 0 | Z25: 0 | AA25: 0 | AB25: 0 | AC25: 0 | AD25: 30
G26: 0 | H26: 0 | I26: 0 | J26: 0 | K26: 0 | L26: 0 | M26: 0 | N26: 0 | O26: 0 | P26: 0 | Q26: 0 | R26: 0 | S26: 0 | T26: 0 | U26: 0 | V26: 0 | W26: 0 | X26: 0 | Y26: 0 | Z26: 0 | AA26: 0 | AB26: 0 | AC26: 0 | AD26: 0
G27: 0 | H27: 0 | I27: 0 | J27: 0 | K27: 0 | L27: 0 | M27: 0 | N27: 0 | O27: 0 | P27: 0 | Q27: 0 | R27: 0 | S27: 0 | T27: 0 | U27: 0 | V27: 0 | W27: 0 | X27: 0 | Y27: 0 | Z27: 0 | AA27: 0 | AB27: 0 | AC27: 0 | AD27: 0
G28: 0 | H28: 0 | I28: 0 | J28: 0 | K28: 0 | L28: 0 | M28: 0 | N28: 0 | O28: 0 | P28: 0 | Q28: 0 | R28: 0 | S28: 0 | T28: 0 | U28: 0 | V28: 0 | W28: 0 | X28: 0 | Y28: 0 | Z28: 0 | AA28: 0 | AB28: 0 | AC28: 0 | AD28: 0
... G43: 0 | H43: 0 | I43: 0 | J43: 0 | K43: 0 | L43: 0 | M43: 0 | N43: 0 | O43: 0 | P43: 0 | Q43: 0 | R43: 0 | S43: 0 | T43: 0 | U43: 0 | V43: 0 | W43: 0 | X43: 0 | Y43: 0 | Z43: 0 | AA43: 0 | AB43: 0 | AC43: 0 | AD43: 0

Sheet FAO
A1: Period | B1: 1 | C1: 2 | D1: 3 | E1: 4 | F1: 5 | G1: 6 | H1: 7 | I1: 8 | J1: 9 | K1: 10 | L1: 11 | M1: 12 | N1: 13 | O1: 14 | P1: 15 | Q1: 16 | R1: 17 | S1: 18 | T1: 19 | U1: 20 | V1: 21 | X1: 22 | Y1: 23 | Z1: 24
A2: Length (y) | B2: 5 | C2: 5 | D2: 5 | E2: 5 | F2: 5 | G2: 5 | H2: 5 | I2: 5 | J2: 5 | K2: 5 | L2: 5 | M2: 5 | N2: 5 | O2: 5 | P2: 5 | Q2: 5 | R2: 5 | S2: 5 | T2: 5 | U2: 5 | V2: 5 | X2: 5 | Y2: 5 | Z2: 5
A3: Price - SEK
A4: =Factors!B2 -> PinTim | B4: 0 | C4: =B4 -> 0 | D4: =C4 -> 0 | E4: =D4 -> 0 | F4: =E4 -> 0 | G4: =F4 -> 0 | H4: =G4 -> 0 | I4: =H4 -> 0 | J4: =I4 -> 0 | ... V4: =U4 -> 0 | X4: =V4 -> 0 | Y4: =X4 -> 0 | Z4: =Y4 -> 0
A5: =Factors!B3 -> PinPuw | B5: 0 | C5: =B5 -> 0 | D5: =C5 -> 0 | E5: =D5 -> 0 | F5: =E5 -> 0 | G5: =F5 -> 0 | H5: =G5 -> 0 | I5: =H5 -> 0 | J5: =I5 -> 0 | ... V5: =U5 -> 0 | X5: =V5 -> 0 | Y5: =X5 -> 0 | Z5: =Y5 -> 0
A6: =Factors!B4 -> SprTim | B6: 0 | C6: =B6 -> 0 | D6: =C6 -> 0 | E6: =D6 -> 0 | F6: =E6 -> 0 | G6: =F6 -> 0 | H6: =G6 -> 0 | I6: =H6 -> 0 | J6: =I6 -> 0 | ... V6: =U6 -> 0 | X6: =V6 -> 0 | Y6: =X6 -> 0 | Z6: =Y6 -> 0
A7: =Factors!B5 -> SprPuw | B7: 0 | C7: =B7 -> 0 | D7: =C7 -> 0 | E7: =D7 -> 0 | F7: =E7 -> 0 | G7: =F7 -> 0 | H7: =G7 -> 0 | I7: =H7 -> 0 | J7: =I7 -> 0 | ... V7: =U7 -> 0 | X7: =V7 -> 0 | Y7: =X7 -> 0 | Z7: =Y7 -> 0
A8: =Factors!B7 -> Decids | B8: 0 | C8: =B8 -> 0 | D8: =C8 -> 0 | E8: =D8 -> 0 | F8: =E8 -> 0 | G8: =F8 -> 0 | H8: =G8 -> 0 | I8: =H8 -> 0 | J8: =I8 -> 0 | ... V8: =U8 -> 0 | X8: =V8 -> 0 | Y8: =X8 -> 0 | Z8: =Y8 -> 0
A9: =Factors!B8 -> Sawdst | B9: 0 | C9: =B9 -> 0 | D9: =C9 -> 0 | E9: =D9 -> 0 | F9: =E9 -> 0 | G9: =F9 -> 0 | H9: =G9 -> 0 | I9: =H9 -> 0 | J9: =I9 -> 0 | ... V9: =U9 -> 0 | X9: =V9 -> 0 | Y9: =X9 -> 0 | Z9: =Y9 -> 0
A10: =Factors!B9 -> Chips_ | B10: 0 | C10: =B10 -> 0 | D10: =C10 -> 0 | E10: =D10 -> 0 | F10: =E10 -> 0 | G10: =F10 -> 0 | H10: =G10 -> 0 | I10: =H10 -> 0 | J10: =I10 -> 0 | ... V10: =U10 -> 0 | X10: =V10 -> 0 | Y10: =X10 -> 0 | Z10: =Y10 -> 0
A11: =Factors!B10 -> ResStm | B11: 0 | C11: 0 | D11: 0 | E11: 0 | F11: 0 | G11: 0 | H11: 0 | I11: 0 | J11: 0 | K11: 0 | L11: 0 | M11: 0 | N11: 0 | O11: 0 | P11: 0 | Q11: 0 | R11: 0 | S11: 0 | T11: 0 | U11: 0 | V11: 0 | X11: 0 | Y11: 0 | Z11: 0
A12: =Factors!B11 -> ResRot | B12: 2152.3304 | C12: 0 | D12: 0 | E12: 0 | F12: 0 | G12: 0 | H12: 0 | I12: 0 | J12: 0 | K12: 0 | L12: 0 | M12: 0 | N12: 0 | O12: 0 | P12: 0 | Q12: 0 | R12: 0 | S12: 0 | T12: 0 | U12: 0 | V12: 0 | X12: 0 | Y12: 0 | Z12: 0
A13: =Factors!B15 -> Sawnco | B13: 111 | C13: =B13 -> 111 | D13: =C13 -> 111 | E13: =D13 -> 111 | F13: =E13 -> 111 | G13: =F13 -> 111 | H13: =G13 -> 111 | I13: =H13 -> 111 | J13: =I13 -> 111 | ... V13: =U13 -> 111 | X13: =V13 -> 111 | Y13: =X13 -> 111 | Z13: =Y13 -> 111
A14: =Factors!B16 -> Sawnbe | B14: 3000 | C14: 3000 | D14: 3000 | E14: 3000 | F14: 3000 | G14: 3000 | H14: 3000 | I14: 3000 | J14: 3000 | K14: 3000 | L14: 3000 | M14: 3000 | N14: 3000 | O14: 3000 | P14: 3000 | Q14: 3000 | R14: 3000 | S14: 3000 | T14: 3000 | U14: 3000 | V14: 3000 | X14: 3000 | Y14: 3000 | Z14: 3000
A15: =Factors!B17 -> Heat__ | B15: 600 | C15: =B15 -> 600 | D15: =C15 -> 600 | E15: =D15 -> 600 | F15: =E15 -> 600 | G15: =F15 -> 600 | H15: =G15 -> 600 | I15: =H15 -> 600 | J15: =I15 -> 600 | ... V15: =U15 -> 600 | X15: =V15 -> 600 | Y15: =X15 -> 600 | Z15: =Y15 -> 600
A16: =Factors!B18 -> Electr | B16: 651 | C16: =B16 -> 651 | D16: =C16 -> 651 | E16: =D16 -> 651 | F16: =E16 -> 651 | G16: =F16 -> 651 | H16: =G16 -> 651 | I16: =H16 -> 651 | J16: =I16 -> 651 | ... V16: =U16 -> 651 | X16: =V16 -> 651 | Y16: =X16 -> 651 | Z16: =Y16 -> 651
A17: =Factors!B19 -> BioFue | B17: 650 | C17: =B17 -> 650 | D17: =C17 -> 650 | E17: =D17 -> 650 | F17: =E17 -> 650 | G17: =F17 -> 650 | H17: =G17 -> 650 | I17: =H17 -> 650 | J17: =I17 -> 650 | ... V17: =U17 -> 650 | X17: =V17 -> 650 | Y17: =X17 -> 650 | Z17: =Y17 -> 650
A18: =Factors!B20 -> PuChem | B18: 5671.6872 | C18: =B18 -> 5671.6872 | D18: =C18 -> 5671.6872 | E18: =D18 -> 5671.6872 | F18: =E18 -> 5671.6872 | G18: =F18 -> 5671.6872 | H18: =G18 -> 5671.6872 | I18: =H18 -> 5671.6872 | J18: =I18 -> 5671.6872 | ... V18: =U18 -> 5671.6872 | X18: =V18 -> 5671.6872 | Y18: =X18 -> 5671.6872 | Z18: =Y18 -> 5671.6872
A19: =Factors!B21 -> PuMech | B19: 4521.8223 | C19: =B19 -> 4521.8223 | D19: =C19 -> 4521.8223 | E19: =D19 -> 4521.8223 | F19: =E19 -> 4521.8223 | G19: =F19 -> 4521.8223 | H19: =G19 -> 4521.8223 | I19: =H19 -> 4521.8223 | J19: =I19 -> 4521.8223 | ... V19: =U19 -> 4521.8223 | X19: =V19 -> 4521.8223 | Y19: =X19 -> 4521.8223 | Z19: =Y19 -> 4521.8223
A20: =Factors!B22 -> PuDiss | B20: 7543.8623 | C20: =B20 -> 7543.8623 | D20: =C20 -> 7543.8623 | E20: =D20 -> 7543.8623 | F20: =E20 -> 7543.8623 | G20: =F20 -> 7543.8623 | H20: =G20 -> 7543.8623 | I20: =H20 -> 7543.8623 | J20: =I20 -> 7543.8623 | ... V20: =U20 -> 7543.8623 | X20: =V20 -> 7543.8623 | Y20: =X20 -> 7543.8623 | Z20: =Y20 -> 7543.8623
A21: =Factors!B23 -> PaChem | B21: 7987.3416 | C21: =B21 -> 7987.3416 | D21: =C21 -> 7987.3416 | E21: =D21 -> 7987.3416 | F21: =E21 -> 7987.3416 | G21: =F21 -> 7987.3416 | H21: =G21 -> 7987.3416 | I21: =H21 -> 7987.3416 | J21: =I21 -> 7987.3416 | ... V21: =U21 -> 7987.3416 | X21: =V21 -> 7987.3416 | Y21: =X21 -> 7987.3416 | Z21: =Y21 -> 7987.3416
A22: =Factors!B24 -> OtChem | B22: 8979.0978 | C22: =B22 -> 8979.0978 | D22: =C22 -> 8979.0978 | E22: =D22 -> 8979.0978 | F22: =E22 -> 8979.0978 | G22: =F22 -> 8979.0978 | H22: =G22 -> 8979.0978 | I22: =H22 -> 8979.0978 | J22: =I22 -> 8979.0978 | ... V22: =U22 -> 8979.0978 | X22: =V22 -> 8979.0978 | Y22: =X22 -> 8979.0978 | Z22: =Y22 -> 8979.0978
A23: =Factors!B25 -> OtMech | B23: 6194.7449 | C23: =B23 -> 6194.7449 | D23: =C23 -> 6194.7449 | E23: =D23 -> 6194.7449 | F23: =E23 -> 6194.7449 | G23: =F23 -> 6194.7449 | H23: =G23 -> 6194.7449 | I23: =H23 -> 6194.7449 | J23: =I23 -> 6194.7449 | ... V23: =U23 -> 6194.7449 | X23: =V23 -> 6194.7449 | Y23: =X23 -> 6194.7449 | Z23: =Y23 -> 6194.7449
A24: =Factors!B26 -> NwMech | B24: 5203.8885 | C24: =B24 -> 5203.8885 | D24: =C24 -> 5203.8885 | E24: =D24 -> 5203.8885 | F24: =E24 -> 5203.8885 | G24: =F24 -> 5203.8885 | H24: =G24 -> 5203.8885 | I24: =H24 -> 5203.8885 | J24: =I24 -> 5203.8885 | ... V24: =U24 -> 5203.8885 | X24: =V24 -> 5203.8885 | Y24: =X24 -> 5203.8885 | Z24: =Y24 -> 5203.8885
A26: Quantity for demand function (elasticity < 0)
A27: =Factors!B2 -> PinTim | B27: 0 | C27: =B27 -> 0 | D27: =C27 -> 0 | E27: =D27 -> 0 | F27: =E27 -> 0 | G27: =F27 -> 0 | H27: =G27 -> 0 | I27: =H27 -> 0 | J27: =I27 -> 0 | ... V27: =U27 -> 0 | X27: =V27 -> 0 | Y27: =X27 -> 0 | Z27: =Y27 -> 0
A28: =Factors!B3 -> PinPuw | B28: 0 | C28: =B28 -> 0 | D28: =C28 -> 0 | E28: =D28 -> 0 | F28: =E28 -> 0 | G28: =F28 -> 0 | H28: =G28 -> 0 | I28: =H28 -> 0 | J28: =I28 -> 0 | ... V28: =U28 -> 0 | X28: =V28 -> 0 | Y28: =X28 -> 0 | Z28: =Y28 -> 0
A29: =Factors!B4 -> SprTim | B29: 0 | C29: =B29 -> 0 | D29: =C29 -> 0 | E29: =D29 -> 0 | F29: =E29 -> 0 | G29: =F29 -> 0 | H29: =G29 -> 0 | I29: =H29 -> 0 | J29: =I29 -> 0 | ... V29: =U29 -> 0 | X29: =V29 -> 0 | Y29: =X29 -> 0 | Z29: =Y29 -> 0
A30: =Factors!B5 -> SprPuw | B30: 0 | C30: =B30 -> 0 | D30: =C30 -> 0 | E30: =D30 -> 0 | F30: =E30 -> 0 | G30: =F30 -> 0 | H30: =G30 -> 0 | I30: =H30 -> 0 | J30: =I30 -> 0 | ... V30: =U30 -> 0 | X30: =V30 -> 0 | Y30: =X30 -> 0 | Z30: =Y30 -> 0
A31: =Factors!B7 -> Decids | B31: 0 | C31: =B31 -> 0 | D31: =C31 -> 0 | E31: =D31 -> 0 | F31: =E31 -> 0 | G31: =F31 -> 0 | H31: =G31 -> 0 | I31: =H31 -> 0 | J31: =I31 -> 0 | ... V31: =U31 -> 0 | X31: =V31 -> 0 | Y31: =X31 -> 0 | Z31: =Y31 -> 0
A32: =Factors!B8 -> Sawdst | B32: 0 | C32: =B32 -> 0 | D32: =C32 -> 0 | E32: =D32 -> 0 | F32: =E32 -> 0 | G32: =F32 -> 0 | H32: =G32 -> 0 | I32: =H32 -> 0 | J32: =I32 -> 0 | ... V32: =U32 -> 0 | X32: =V32 -> 0 | Y32: =X32 -> 0 | Z32: =Y32 -> 0
A33: =Factors!B9 -> Chips_ | B33: 0 | C33: =B33 -> 0 | D33: =C33 -> 0 | E33: =D33 -> 0 | F33: =E33 -> 0 | G33: =F33 -> 0 | H33: =G33 -> 0 | I33: =H33 -> 0 | J33: =I33 -> 0 | ... V33: =U33 -> 0 | X33: =V33 -> 0 | Y33: =X33 -> 0 | Z33: =Y33 -> 0
A34: =Factors!B10 -> ResStm | B34: 0 | C34: 0 | D34: 0 | E34: 0 | F34: 0 | G34: 0 | H34: 0 | I34: 0 | J34: 0 | K34: 0 | L34: 0 | M34: 0 | N34: 0 | O34: 0 | P34: 0 | Q34: 0 | R34: 0 | S34: 0 | T34: 0 | U34: 0 | V34: 0 | X34: 0 | Y34: 0 | Z34: 0
A35: =Factors!B11 -> ResRot | B35: 0 | C35: 0 | D35: 0 | E35: 0 | F35: 0 | G35: 0 | H35: 0 | I35: 0 | J35: 0 | K35: 0 | L35: 0 | M35: 0 | N35: 0 | O35: 0 | P35: 0 | Q35: 0 | R35: 0 | S35: 0 | T35: 0 | U35: 0 | V35: 0 | X35: 0 | Y35: 0 | Z35: 0
A36: =Factors!B15 -> Sawnco | B36: 18630000 | C36: 18816300 | D36: 19004463 | E36: 19194508 | F36: 19386453 | G36: 19580317 | H36: 19580317 | I36: 19580317 | J36: 19580317 | K36: 19580317 | L36: 19580317 | M36: 19580317 | N36: 19580317 | O36: 19580317 | P36: 19580317 | Q36: 19580317 | R36: 19580317 | S36: 19580317 | T36: 19580317 | U36: 19580317 | V36: 19580317 | X36: 19580317 | Y36: 19580317 | Z36: 19580317
A37: =Factors!B16 -> Sawnbe | B37: 111 | C37: 0 | D37: 0 | E37: 0 | F37: 0 | G37: 0 | H37: 0 | I37: 0 | J37: 0 | K37: 0 | L37: 0 | M37: 0 | N37: 0 | O37: 0 | P37: 0 | Q37: 0 | R37: 0 | S37: 0 | T37: 0 | U37: 0 | V37: 0
A38: =Factors!B17 -> Heat__ | B38: 0 | C38: 0 | D38: 0 | E38: 0 | F38: 0 | G38: 0 | H38: 0 | I38: 0 | J38: 0 | K38: 0 | L38: 0 | M38: 0 | N38: 0 | O38: 0 | P38: 0 | Q38: 0 | R38: 0 | S38: 0 | T38: 0 | U38: 0 | V38: 0 | X38: 17250000 | Y38: 17250000 | Z38: 17250000
A39: =Factors!B18 -> Electr | B39: 0 | C39: 0 | D39: 0 | E39: 0 | F39: 0 | G39: 0 | H39: 0 | I39: 0 | J39: 0 | K39: 0 | L39: 0 | M39: 0 | N39: 0 | O39: 0 | P39: 0 | Q39: 0 | R39: 0 | S39: 0 | T39: 0 | U39: 0 | V39: 0 | X39: 0 | Y39: 0 | Z39: 0
A40: =Factors!B19 -> BioFue | B40: 0 | C40: 0 | D40: 0 | E40: 0 | F40: 0 | G40: 0 | H40: 0 | I40: 0 | J40: 0 | K40: 0 | L40: 0 | M40: 0 | N40: 0 | O40: 0 | P40: 0 | Q40: 0 | R40: 0 | S40: 0 | T40: 0 | U40: 0 | V40: 0 | X40: 0 | Y40: 0 | Z40: 0
A41: =Factors!B20 -> PuChem | B41: 3290524 | C41: 3435447.1 | D41: 3586753 | E41: 3744722.7 | F41: 3909649.9 | G41: 4081840.9 | H41: 4081840.9 | I41: 4081840.9 | J41: 4081840.9 | K41: 4081840.9 | L41: 4081840.9 | M41: 4081840.9 | N41: 4081840.9 | O41: 4081840.9 | P41: 4081840.9 | Q41: 4081840.9 | R41: 4081840.9 | S41: 4081840.9 | T41: 4081840.9 | U41: 4081840.9 | V41: 4081840.9 | X41: 4081840.9 | Y41: 4081840.9 | Z41: 4081840.9
A42: =Factors!B21 -> PuMech | B42: 409948 | C42: 403929.61 | D42: 397999.58 | E42: 392156.61 | F42: 386399.42 | G42: 380726.74 | H42: 380726.74 | I42: 380726.74 | J42: 380726.74 | K42: 380726.74 | L42: 380726.74 | M42: 380726.74 | N42: 380726.74 | O42: 380726.74 | P42: 380726.74 | Q42: 380726.74 | R42: 380726.74 | S42: 380726.74 | T42: 380726.74 | U42: 380726.74 | V42: 380726.74 | X42: 380726.74 | Y42: 380726.74 | Z42: 380726.74
A43: =Factors!B22 -> PuDiss | B43: 336337 | C43: 351150.14 | D43: 366615.69 | E43: 382762.38 | F43: 399620.22 | G43: 417220.51 | H43: 417220.51 | I43: 417220.51 | J43: 417220.51 | K43: 417220.51 | L43: 417220.51 | M43: 417220.51 | N43: 417220.51 | O43: 417220.51 | P43: 417220.51 | Q43: 417220.51 | R43: 417220.51 | S43: 417220.51 | T43: 417220.51 | U43: 417220.51 | V43: 417220.51 | X43: 417220.51 | Y43: 417220.51 | Z43: 417220.51
A44: =Factors!B23 -> PaChem | B44: 6362000 | C44: 6642198.7 | D44: 6934738.2 | E44: 7240161.8 | F44: 7559037 | G44: 7891956.3 | H44: 7891956.3 | I44: 7891956.3 | J44: 7891956.3 | K44: 7891956.3 | L44: 7891956.3 | M44: 7891956.3 | N44: 7891956.3 | O44: 7891956.3 | P44: 7891956.3 | Q44: 7891956.3 | R44: 7891956.3 | S44: 7891956.3 | T44: 7891956.3 | U44: 7891956.3 | V44: 7891956.3 | X44: 7891956.3 | Y44: 7891956.3 | Z44: 7891956.3
A45: =Factors!B24 -> OtChem | B45: 462869 | C45: 483254.93 | D45: 504538.72 | E45: 526759.89 | F45: 549959.74 | G45: 574181.38 | H45: 574181.38 | I45: 574181.38 | J45: 574181.38 | K45: 574181.38 | L45: 574181.38 | M45: 574181.38 | N45: 574181.38 | O45: 574181.38 | P45: 574181.38 | Q45: 574181.38 | R45: 574181.38 | S45: 574181.38 | T45: 574181.38 | U45: 574181.38 | V45: 574181.38 | X45: 574181.38 | Y45: 574181.38 | Z45: 574181.38
A46: =Factors!B25 -> OtMech | B46: 1372303 | C46: 1352156.4 | D46: 1332305.6 | E46: 1312746.2 | F46: 1293474 | G46: 1274484.7 | H46: 1274484.7 | I46: 1274484.7 | J46: 1274484.7 | K46: 1274484.7 | L46: 1274484.7 | M46: 1274484.7 | N46: 1274484.7 | O46: 1274484.7 | P46: 1274484.7 | Q46: 1274484.7 | R46: 1274484.7 | S46: 1274484.7 | T46: 1274484.7 | U46: 1274484.7 | V46: 1274484.7 | X46: 1274484.7 | Y46: 1274484.7 | Z46: 1274484.7
A47: =Factors!B26 -> NwMech | B47: 889000 | C47: 862897.44 | D47: 837561.31 | E47: 812969.08 | F47: 789098.92 | G47: 765929.63 | H47: 765929.63 | I47: 765929.63 | J47: 765929.63 | K47: 765929.63 | L47: 765929.63 | M47: 765929.63 | N47: 765929.63 | O47: 765929.63 | P47: 765929.63 | Q47: 765929.63 | R47: 765929.63 | S47: 765929.63 | T47: 765929.63 | U47: 765929.63 | V47: 765929.63 | X47: 765929.63 | Y47: 765929.63 | Z47: 765929.63
A50: ImportPrices
A51: =Factors!B2 -> PinTim | B51: 0 | C51: 0 | D51: 0 | E51: 0 | F51: 0 | G51: 0 | H51: 0 | I51: 0 | J51: 0 | K51: 0 | L51: 0 | M51: 0 | N51: 0 | O51: 0 | P51: 0 | Q51: 0 | R51: 0 | S51: 0 | T51: 0 | U51: 0 | V51: 0 | X51: 1 | Y51: 1 | Z51: 1
A52: =Factors!B3 -> PinPuw | B52: 0 | C52: 0 | D52: 0 | E52: 0 | F52: 0 | G52: 0 | H52: 0 | I52: 0 | J52: 0 | K52: 0 | L52: 0 | M52: 0 | N52: 0 | O52: 0 | P52: 0 | Q52: 0 | R52: 0 | S52: 0 | T52: 0 | U52: 0 | V52: 0 | X52: 1 | Y52: 1 | Z52: 1
A53: =Factors!B4 -> SprTim | B53: 0 | C53: 0 | D53: 0 | E53: 0 | F53: 0 | G53: 0 | H53: 0 | I53: 0 | J53: 0 | K53: 0 | L53: 0 | M53: 0 | N53: 0 | O53: 0 | P53: 0 | Q53: 0 | R53: 0 | S53: 0 | T53: 0 | U53: 0 | V53: 0 | X53: 1 | Y53: 1 | Z53: 1
A54: =Factors!B5 -> SprPuw | B54: 0 | C54: 0 | D54: 0 | E54: 0 | F54: 0 | G54: 0 | H54: 0 | I54: 0 | J54: 0 | K54: 0 | L54: 0 | M54: 0 | N54: 0 | O54: 0 | P54: 0 | Q54: 0 | R54: 0 | S54: 0 | T54: 0 | U54: 0 | V54: 0 | X54: 1 | Y54: 1 | Z54: 1
A55: =Factors!B7 -> Decids | B55: 0 | C55: 0 | D55: 0 | E55: 0 | F55: 0 | G55: 0 | H55: 0 | I55: 0 | J55: 0 | K55: 0 | L55: 0 | M55: 0 | N55: 0 | O55: 0 | P55: 0 | Q55: 0 | R55: 0 | S55: 0 | T55: 0 | U55: 0 | V55: 0 | X55: 1 | Y55: 1 | Z55: 1
A56: =Factors!B8 -> Sawdst | B56: =B9 -> 0 | C56: =C9 -> 0 | D56: =D9 -> 0 | E56: =E9 -> 0 | F56: =F9 -> 0 | G56: =G9 -> 0 | H56: =H9 -> 0 | I56: =I9 -> 0 | ... V56: =V9 -> 0 | X56: =X9 -> 0 | Y56: =Y9 -> 0 | Z56: =Z9 -> 0
A57: =Factors!B9 -> Chips_ | B57: =B10 -> 0 | C57: =C10 -> 0 | D57: =D10 -> 0 | E57: =E10 -> 0 | F57: =F10 -> 0 | G57: =G10 -> 0 | H57: =H10 -> 0 | I57: =I10 -> 0 | ... V57: =V10 -> 0 | X57: =X10 -> 0 | Y57: =Y10 -> 0 | Z57: =Z10 -> 0
A58: =Factors!B10 -> ResStm | B58: =0 -> 0 | C58: =B58 -> 0 | D58: =C58 -> 0 | E58: =D58 -> 0 | F58: =E58 -> 0 | G58: =F58 -> 0 | H58: =G58 -> 0 | I58: =H58 -> 0 | J58: =I58 -> 0 | ... V58: =U58 -> 0 | X58: =X15*ConvFact!$A$1*2 -> 5880 | Y58: =Y15*ConvFact!$A$1*2 -> 5880 | Z58: =Z15*ConvFact!$A$1*2 -> 5880
A59: =Factors!B11 -> ResRot | B59: 0 | C59: 0 | D59: 0 | E59: 0 | F59: 0 | G59: 0 | H59: 0 | I59: 0 | J59: 0 | K59: 0 | L59: 0 | M59: 0 | N59: 0 | O59: 0 | P59: 0 | Q59: 0 | R59: 0 | S59: 0 | T59: 0 | U59: 0 | V59: 0 | X59: 0 | Y59: 0 | Z59: 0
A60: =Factors!B15 -> Sawnco | B60: 0 | C60: 0 | D60: 0 | E60: 0 | F60: 0 | G60: 0 | H60: 0 | I60: 0 | J60: 0 | K60: 0 | L60: 0 | M60: 0 | N60: 0 | O60: 0 | P60: 0 | Q60: 0 | R60: 0 | S60: 0 | T60: 0 | U60: 0 | V60: 0 | X60: 0 | Y60: 0 | Z60: 0
A61: =Factors!B16 -> Sawnbe | B61: 0 | C61: 0 | D61: 0 | E61: 0 | F61: 0 | G61: 0 | H61: 0 | I61: 0 | J61: 0 | K61: 0 | L61: 0 | M61: 0 | N61: 0 | O61: 0 | P61: 0 | Q61: 0 | R61: 0 | S61: 0 | T61: 0 | U61: 0 | V61: 0
A62: =Factors!B17 -> Heat__ | B62: 0 | C62: 0 | D62: 0 | E62: 0 | F62: 0 | G62: 0 | H62: 0 | I62: 0 | J62: 0 | K62: 0 | L62: 0 | M62: 0 | N62: 0 | O62: 0 | P62: 0 | Q62: 0 | R62: 0 | S62: 0 | T62: 0 | U62: 0 | V62: 0 | X62: 0 | Y62: 0 | Z62: 0
A63: =Factors!B18 -> Electr | B63: 0 | C63: 0 | D63: 0 | E63: 0 | F63: 0 | G63: 0 | H63: 0 | I63: 0 | J63: 0 | K63: 0 | L63: 0 | M63: 0 | N63: 0 | O63: 0 | P63: 0 | Q63: 0 | R63: 0 | S63: 0 | T63: 0 | U63: 0 | V63: 0 | X63: 0 | Y63: 0 | Z63: 0
A64: =Factors!B19 -> BioFue | B64: 0 | C64: 0 | D64: 0 | E64: 0 | F64: 0 | G64: 0 | H64: 0 | I64: 0 | J64: 0 | K64: 0 | L64: 0 | M64: 0 | N64: 0 | O64: 0 | P64: 0 | Q64: 0 | R64: 0 | S64: 0 | T64: 0 | U64: 0 | V64: 0 | X64: 0 | Y64: 0 | Z64: 0
A65: =Factors!B20 -> PuChem | B65: 0 | C65: 0 | D65: 0 | E65: 0 | F65: 0 | G65: 0 | H65: 0 | I65: 0 | J65: 0 | K65: 0 | L65: 0 | M65: 0 | N65: 0 | O65: 0 | P65: 0 | Q65: 0 | R65: 0 | S65: 0 | T65: 0 | U65: 0 | V65: 0 | X65: 0 | Y65: 0 | Z65: 0
A66: =Factors!B21 -> PuMech | B66: 0 | C66: 0 | D66: 0 | E66: 0 | F66: 0 | G66: 0 | H66: 0 | I66: 0 | J66: 0 | K66: 0 | L66: 0 | M66: 0 | N66: 0 | O66: 0 | P66: 0 | Q66: 0 | R66: 0 | S66: 0 | T66: 0 | U66: 0 | V66: 0 | X66: 0 | Y66: 0 | Z66: 0
A67: =Factors!B22 -> PuDiss | B67: 0 | C67: 0 | D67: 0 | E67: 0 | F67: 0 | G67: 0 | H67: 0 | I67: 0 | J67: 0 | K67: 0 | L67: 0 | M67: 0 | N67: 0 | O67: 0 | P67: 0 | Q67: 0 | R67: 0 | S67: 0 | T67: 0 | U67: 0 | V67: 0 | X67: 0 | Y67: 0 | Z67: 0
A68: =Factors!B23 -> PaChem | B68: 0 | C68: 0 | D68: 0 | E68: 0 | F68: 0 | G68: 0 | H68: 0 | I68: 0 | J68: 0 | K68: 0 | L68: 0 | M68: 0 | N68: 0 | O68: 0 | P68: 0 | Q68: 0 | R68: 0 | S68: 0 | T68: 0 | U68: 0 | V68: 0 | X68: 0 | Y68: 0 | Z68: 0
A69: =Factors!B24 -> OtChem | B69: 0 | C69: 0 | D69: 0 | E69: 0 | F69: 0 | G69: 0 | H69: 0 | I69: 0 | J69: 0 | K69: 0 | L69: 0 | M69: 0 | N69: 0 | O69: 0 | P69: 0 | Q69: 0 | R69: 0 | S69: 0 | T69: 0 | U69: 0 | V69: 0 | X69: 0 | Y69: 0 | Z69: 0
A70: =Factors!B25 -> OtMech | B70: 0 | C70: 0 | D70: 0 | E70: 0 | F70: 0 | G70: 0 | H70: 0 | I70: 0 | J70: 0 | K70: 0 | L70: 0 | M70: 0 | N70: 0 | O70: 0 | P70: 0 | Q70: 0 | R70: 0 | S70: 0 | T70: 0 | U70: 0 | V70: 0 | X70: 0 | Y70: 0 | Z70: 0
A71: =Factors!B26 -> NwMech | B71: 0 | C71: 0 | D71: 0 | E71: 0 | F71: 0 | G71: 0 | H71: 0 | I71: 0 | J71: 0 | K71: 0 | L71: 0 | M71: 0 | N71: 0 | O71: 0 | P71: 0 | Q71: 0 | R71: 0 | S71: 0 | T71: 0 | U71: 0 | V71: 0 | X71: 0 | Y71: 0 | Z71: 0
A73: MaxImports
A74: =Factors!B2 -> PinTim | B74: 400000 | C74: =B74*0.8 -> 320000 | D74: =C74*0.8 -> 256000 | E74: =D74*0.8 -> 204800 | F74: =E74*0.8 -> 163840 | G74: =F74*0.8 -> 131072 | H74: =G74*0.8 -> 104857.6 | I74: =H74*0.8 -> 83886.08 | J74: =I74*0.8 -> 67108.864 | ... V74: =U74*0.8 -> 4611.686 | X74: =V74*0.8 -> 3689.3488 | Y74: =X74*0.8 -> 2951.4791 | Z74: =Y74*0.8 -> 2361.1832
A75: =Factors!B3 -> PinPuw | B75: 1300000 | C75: =B75*0.8 -> 1040000 | D75: =C75*0.8 -> 832000 | E75: =D75*0.8 -> 665600 | F75: =E75*0.8 -> 532480 | G75: =F75*0.8 -> 425984 | H75: =G75*0.8 -> 340787.2 | I75: =H75*0.8 -> 272629.76 | J75: =I75*0.8 -> 218103.81 | ... V75: =U75*0.8 -> 14987.98 | X75: =V75*0.8 -> 11990.384 | Y75: =X75*0.8 -> 9592.3069 | Z75: =Y75*0.8 -> 7673.8455
A76: =Factors!B4 -> SprTim | B76: 500000 | C76: =B76*0.8 -> 400000 | D76: =C76*0.8 -> 320000 | E76: =D76*0.8 -> 256000 | F76: =E76*0.8 -> 204800 | G76: =F76*0.8 -> 163840 | H76: =G76*0.8 -> 131072 | I76: =H76*0.8 -> 104857.6 | J76: =I76*0.8 -> 83886.08 | ... V76: =U76*0.8 -> 5764.6075 | X76: =V76*0.8 -> 4611.686 | Y76: =X76*0.8 -> 3689.3488 | Z76: =Y76*0.8 -> 2951.4791
A77: =Factors!B5 -> SprPuw | B77: 1800000 | C77: =B77*0.8 -> 1440000 | D77: =C77*0.8 -> 1152000 | E77: =D77*0.8 -> 921600 | F77: =E77*0.8 -> 737280 | G77: =F77*0.8 -> 589824 | H77: =G77*0.8 -> 471859.2 | I77: =H77*0.8 -> 377487.36 | J77: =I77*0.8 -> 301989.89 | ... V77: =U77*0.8 -> 20752.587 | X77: =V77*0.8 -> 16602.07 | Y77: =X77*0.8 -> 13281.656 | Z77: =Y77*0.8 -> 10625.325
A78: =Factors!B7 -> Decids | B78: 2700000 | C78: =B78*0.8 -> 2160000 | D78: =C78*0.8 -> 1728000 | E78: =D78*0.8 -> 1382400 | F78: =E78*0.8 -> 1105920 | G78: =F78*0.8 -> 884736 | H78: =G78*0.8 -> 707788.8 | I78: =H78*0.8 -> 566231.04 | J78: =I78*0.8 -> 452984.83 | ... V78: =U78*0.8 -> 31128.881 | X78: =V78*0.8 -> 24903.104 | Y78: =X78*0.8 -> 19922.484 | Z78: =Y78*0.8 -> 15937.987
A79: =Factors!B8 -> Sawdst | B79: 0 | C79: 0 | D79: 0 | E79: 0 | F79: 0 | G79: 0 | H79: 0 | I79: 0 | J79: 0 | K79: 0 | L79: 0 | M79: 0 | N79: 0 | O79: 0 | P79: 0 | Q79: 0 | R79: 0 | S79: 0 | T79: 0 | U79: 0 | V79: 0 | X79: 0 | Y79: 0 | Z79: 0
A80: =Factors!B9 -> Chips_ | B80: 0 | C80: 0 | D80: 0 | E80: 0 | F80: 0 | G80: 0 | H80: 0 | I80: 0 | J80: 0 | K80: 0 | L80: 0 | M80: 0 | N80: 0 | O80: 0 | P80: 0 | Q80: 0 | R80: 0 | S80: 0 | T80: 0 | U80: 0 | V80: 0 | X80: 0 | Y80: 0 | Z80: 0
A81: =Factors!B10 -> ResStm | B81: 100000000 | C81: 100000000 | D81: 100000000 | E81: 100000000 | F81: 100000000 | G81: 100000000 | H81: 100000000 | I81: 100000000 | J81: 100000000 | K81: 100000000 | L81: 100000000 | M81: 100000000 | N81: 100000000 | O81: 100000000 | P81: 100000000 | Q81: 100000000 | R81: 100000000 | S81: 100000000 | T81: 100000000 | U81: 100000000 | V81: 100000000 | X81: 100000000 | Y81: 100000000 | Z81: 100000000
A82: =Factors!B11 -> ResRot | B82: 0 | C82: 0 | D82: 0 | E82: 0 | F82: 0 | G82: 0 | H82: 0 | I82: 0 | J82: 0 | K82: 0 | L82: 0 | M82: 0 | N82: 0 | O82: 0 | P82: 0 | Q82: 0 | R82: 0 | S82: 0 | T82: 0 | U82: 0 | V82: 0 | X82: 0 | Y82: 0 | Z82: 0
A83: =Factors!B15 -> Sawnco | B83: 0 | C83: 0 | D83: 0 | E83: 0 | F83: 0 | G83: 0 | H83: 0 | I83: 0 | J83: 0 | K83: 0 | L83: 0 | M83: 0 | N83: 0 | O83: 0 | P83: 0 | Q83: 0 | R83: 0 | S83: 0 | T83: 0 | U83: 0 | V83: 0 | X83: 0 | Y83: 0 | Z83: 0
A84: =Factors!B16 -> Sawnbe | B84: 0 | C84: 0 | D84: 0 | E84: 0 | F84: 0 | G84: 0 | H84: 0 | I84: 0 | J84: 0 | K84: 0 | L84: 0 | M84: 0 | N84: 0 | O84: 0 | P84: 0 | Q84: 0 | R84: 0 | S84: 0 | T84: 0 | U84: 0 | V84: 0
A85: =Factors!B17 -> Heat__ | B85: 0 | C85: 0 | D85: 0 | E85: 0 | F85: 0 | G85: 0 | H85: 0 | I85: 0 | J85: 0 | K85: 0 | L85: 0 | M85: 0 | N85: 0 | O85: 0 | P85: 0 | Q85: 0 | R85: 0 | S85: 0 | T85: 0 | U85: 0 | V85: 0 | X85: 0 | Y85: 0 | Z85: 0
A86: =Factors!B18 -> Electr | B86: 0 | C86: 0 | D86: 0 | E86: 0 | F86: 0 | G86: 0 | H86: 0 | I86: 0 | J86: 0 | K86: 0 | L86: 0 | M86: 0 | N86: 0 | O86: 0 | P86: 0 | Q86: 0 | R86: 0 | S86: 0 | T86: 0 | U86: 0 | V86: 0 | X86: 0 | Y86: 0 | Z86: 0
A87: =Factors!B19 -> BioFue | B87: 0 | C87: 0 | D87: 0 | E87: 0 | F87: 0 | G87: 0 | H87: 0 | I87: 0 | J87: 0 | K87: 0 | L87: 0 | M87: 0 | N87: 0 | O87: 0 | P87: 0 | Q87: 0 | R87: 0 | S87: 0 | T87: 0 | U87: 0 | V87: 0 | X87: 0 | Y87: 0 | Z87: 0
A88: =Factors!B20 -> PuChem | B88: 0 | C88: 0 | D88: 0 | E88: 0 | F88: 0 | G88: 0 | H88: 0 | I88: 0 | J88: 0 | K88: 0 | L88: 0 | M88: 0 | N88: 0 | O88: 0 | P88: 0 | Q88: 0 | R88: 0 | S88: 0 | T88: 0 | U88: 0 | V88: 0 | X88: 0 | Y88: 0 | Z88: 0
A89: =Factors!B21 -> PuMech | B89: 0 | C89: 0 | D89: 0 | E89: 0 | F89: 0 | G89: 0 | H89: 0 | I89: 0 | J89: 0 | K89: 0 | L89: 0 | M89: 0 | N89: 0 | O89: 0 | P89: 0 | Q89: 0 | R89: 0 | S89: 0 | T89: 0 | U89: 0 | V89: 0 | X89: 0 | Y89: 0 | Z89: 0
A90: =Factors!B22 -> PuDiss | B90: 0 | C90: 0 | D90: 0 | E90: 0 | F90: 0 | G90: 0 | H90: 0 | I90: 0 | J90: 0 | K90: 0 | L90: 0 | M90: 0 | N90: 0 | O90: 0 | P90: 0 | Q90: 0 | R90: 0 | S90: 0 | T90: 0 | U90: 0 | V90: 0 | X90: 0 | Y90: 0 | Z90: 0
A91: =Factors!B23 -> PaChem | B91: 0 | C91: 0 | D91: 0 | E91: 0 | F91: 0 | G91: 0 | H91: 0 | I91: 0 | J91: 0 | K91: 0 | L91: 0 | M91: 0 | N91: 0 | O91: 0 | P91: 0 | Q91: 0 | R91: 0 | S91: 0 | T91: 0 | U91: 0 | V91: 0 | X91: 0 | Y91: 0 | Z91: 0
A92: =Factors!B24 -> OtChem | B92: 0 | C92: 0 | D92: 0 | E92: 0 | F92: 0 | G92: 0 | H92: 0 | I92: 0 | J92: 0 | K92: 0 | L92: 0 | M92: 0 | N92: 0 | O92: 0 | P92: 0 | Q92: 0 | R92: 0 | S92: 0 | T92: 0 | U92: 0 | V92: 0 | X92: 0 | Y92: 0 | Z92: 0
A93: =Factors!B25 -> OtMech | B93: 0 | C93: 0 | D93: 0 | E93: 0 | F93: 0 | G93: 0 | H93: 0 | I93: 0 | J93: 0 | K93: 0 | L93: 0 | M93: 0 | N93: 0 | O93: 0 | P93: 0 | Q93: 0 | R93: 0 | S93: 0 | T93: 0 | U93: 0 | V93: 0 | X93: 0 | Y93: 0 | Z93: 0
A94: =Factors!B26 -> NwMech | B94: 0 | C94: 0 | D94: 0 | E94: 0 | F94: 0 | G94: 0 | H94: 0 | I94: 0 | J94: 0 | K94: 0 | L94: 0 | M94: 0 | N94: 0 | O94: 0 | P94: 0 | Q94: 0 | R94: 0 | S94: 0 | T94: 0 | U94: 0 | V94: 0 | X94: 0 | Y94: 0 | Z94: 0

Sheet IIASA
A1: Period | B1: 1 | C1: 2 | D1: 3 | E1: 4 | F1: 5 | G1: 6 | H1: 7 | I1: 8 | J1: 9 | K1: 10 | L1: 11 | M1: 12 | N1: 13 | O1: 14 | P1: 15 | Q1: 16 | R1: 17 | S1: 18 | T1: 19 | U1: 20 | V1: 21 | W1: 22 | Y1: 23 | AA1: 22 | AB1: 23 | AC1: 24
A2: Length (y) | B2: 5 | C2: 5 | D2: 5 | E2: 5 | F2: 5 | G2: 5 | H2: 5 | I2: 5 | J2: 5 | K2: 5 | L2: 5 | M2: 5 | N2: 5 | O2: 5 | P2: 5 | Q2: 5 | R2: 5 | S2: 5 | T2: 5 | U2: 5 | V2: 5 | W2: 5 | Y2: 5 | AA2: 5 | AB2: 5 | AC2: 5
A3: Price - SEK
A4: =Factors!B2 -> PinTim | B4: 0 | C4: =B4 -> 0 | D4: =C4 -> 0 | E4: =D4 -> 0 | F4: =E4 -> 0 | G4: =F4 -> 0 | H4: =G4 -> 0 | I4: =H4 -> 0 | J4: =I4 -> 0 | ... W4: =V4 -> 0 | Y4: =W4 -> 0 | AA4: =V4 -> 0 | AB4: =AA4 -> 0 | AC4: =AB4 -> 0
A5: =Factors!B3 -> PinPuw | B5: 0 | C5: =B5 -> 0 | D5: =C5 -> 0 | E5: =D5 -> 0 | F5: =E5 -> 0 | G5: =F5 -> 0 | H5: =G5 -> 0 | I5: =H5 -> 0 | J5: =I5 -> 0 | ... W5: =V5 -> 0 | Y5: =W5 -> 0 | AA5: =V5 -> 0 | AB5: =AA5 -> 0 | AC5: =AB5 -> 0
A6: =Factors!B4 -> SprTim | B6: 0 | C6: =B6 -> 0 | D6: =C6 -> 0 | E6: =D6 -> 0 | F6: =E6 -> 0 | G6: =F6 -> 0 | H6: =G6 -> 0 | I6: =H6 -> 0 | J6: =I6 -> 0 | ... W6: =V6 -> 0 | Y6: =W6 -> 0 | AA6: =V6 -> 0 | AB6: =AA6 -> 0 | AC6: =AB6 -> 0
A7: =Factors!B5 -> SprPuw | B7: 0 | C7: =B7 -> 0 | D7: =C7 -> 0 | E7: =D7 -> 0 | F7: =E7 -> 0 | G7: =F7 -> 0 | H7: =G7 -> 0 | I7: =H7 -> 0 | J7: =I7 -> 0 | ... W7: =V7 -> 0 | Y7: =W7 -> 0 | AA7: =V7 -> 0 | AB7: =AA7 -> 0 | AC7: =AB7 -> 0
A8: =Factors!B7 -> Decids | B8: 0 | C8: =B8 -> 0 | D8: =C8 -> 0 | E8: =D8 -> 0 | F8: =E8 -> 0 | G8: =F8 -> 0 | H8: =G8 -> 0 | I8: =H8 -> 0 | J8: =I8 -> 0 | ... W8: =V8 -> 0 | Y8: =W8 -> 0 | AA8: =V8 -> 0 | AB8: =AA8 -> 0 | AC8: =AB8 -> 0
A9: =Factors!B8 -> Sawdst | B9: 0 | C9: =B9 -> 0 | D9: =C9 -> 0 | E9: =D9 -> 0 | F9: =E9 -> 0 | G9: =F9 -> 0 | H9: =G9 -> 0 | I9: =H9 -> 0 | J9: =I9 -> 0 | ... W9: =V9 -> 0 | Y9: =W9 -> 0 | AA9: =V9 -> 0 | AB9: =AA9 -> 0 | AC9: =AB9 -> 0
A10: =Factors!B9 -> Chips_ | B10: 0 | C10: =B10 -> 0 | D10: =C10 -> 0 | E10: =D10 -> 0 | F10: =E10 -> 0 | G10: =F10 -> 0 | H10: =G10 -> 0 | I10: =H10 -> 0 | J10: =I10 -> 0 | ... W10: =V10 -> 0 | Y10: =W10 -> 0 | AA10: =V10 -> 0 | AB10: =AA10 -> 0 | AC10: =AB10 -> 0
A11: =Factors!B10 -> ResStm | B11: 0 | C11: 0 | D11: 0 | E11: 0 | F11: 0 | G11: 0 | H11: 0 | I11: 0 | J11: 0 | K11: 0 | L11: 0 | M11: 0 | N11: 0 | O11: 0 | P11: 0 | Q11: 0 | R11: 0 | S11: 0 | T11: 0 | U11: 0 | V11: 0 | W11: 0 | Y11: 0 | AA11: 0 | AB11: 0 | AC11: 0
A12: =Factors!B11 -> ResRot | B12: 0 | C12: 0 | D12: 0 | E12: 0 | F12: 0 | G12: 0 | H12: 0 | I12: 0 | J12: 0 | K12: 0 | L12: 0 | M12: 0 | N12: 0 | O12: 0 | P12: 0 | Q12: 0 | R12: 0 | S12: 0 | T12: 0 | U12: 0 | V12: 0 | W12: 0 | Y12: 0 | AA12: 0 | AB12: 0 | AC12: 0
A13: =Factors!B15 -> Sawnco | B13: =[2]IIASA2SweFor!$B$16 -> 2152.3304 | C13: =(B13+D13)/2 -> 2082.7167 | D13: =[2]IIASA2SweFor!$C$16 -> 2013.1031 | E13: =(D13+F13)/2 -> 1998.5887 | F13: =[2]IIASA2SweFor!$D$16 -> 1984.0742 | G13: =(F13+H13)/2 -> 2008.9281 | H13: =[2]IIASA2SweFor!$E$16 -> 2033.7819 | I13: =(H13+J13)/2 -> 2067.9868 | J13: =[2]IIASA2SweFor!$F$16 -> 2102.1917 | K13: =(J13+L13)/2 -> 2134.9267 | L13: =[2]IIASA2SweFor!$G$16 -> 2167.6617 | M13: =(L13+N13)/2 -> 2181.8808 | N13: =[2]IIASA2SweFor!$H$16 -> 2196.0999 | O13: =(N13+P13)/2 -> 2197.2825 | P13: =[2]IIASA2SweFor!$I$16 -> 2198.465 | Q13: =(P13+R13)/2 -> 2175.0299 | R13: =[2]IIASA2SweFor!$J$16 -> 2151.5947 | S13: =R13 -> 2151.5947 | T13: =S13 -> 2151.5947 | U13: =T13 -> 2151.5947 | V13: =U13 -> 2151.5947 | W13: =V13 -> 2151.5947 | Y13: =W13 -> 2151.5947 | AA13: =V13 -> 2151.5947 | AB13: =AA13 -> 2151.5947 | AC13: =AB13 -> 2151.5947
A14: =Factors!B16 -> Sawnbe | B14: =3000 -> 3000 | C14: =$B$14/$B$13*C13 -> 2902.9699 | D14: =$B$14/$B$13*D13 -> 2805.9397 | E14: =$B$14/$B$13*E13 -> 2785.709 | F14: =$B$14/$B$13*F13 -> 2765.4782 | G14: =$B$14/$B$13*G13 -> 2800.1204 | H14: =$B$14/$B$13*H13 -> 2834.7626 | I14: =$B$14/$B$13*I13 -> 2882.4387 | J14: =$B$14/$B$13*J13 -> 2930.1148 | ... W14: =$B$14/$B$13*W13 -> 2998.9747
A15: =Factors!B17 -> Heat__ | B15: 0 | C15: 0 | D15: 0 | E15: 0 | F15: 0 | G15: 0 | H15: 0 | I15: 0 | J15: 0 | K15: 0 | L15: 0 | M15: 0 | N15: 0 | O15: 0 | P15: 0 | Q15: 0 | R15: 0 | S15: 0 | T15: 0 | U15: 0 | V15: 0 | W15: 0 | Y15: 0 | AA15: =V15 -> 0 | AB15: =AA15 -> 0 | AC15: =AB15 -> 0
A16: =Factors!B18 -> Electr | B16: 650 | C16: 650 | D16: 650 | E16: 650 | F16: 650 | G16: 650 | H16: 650 | I16: 650 | J16: 650 | K16: 650 | L16: 650 | M16: 650 | N16: 650 | O16: 650 | P16: 650 | Q16: 650 | R16: 650 | S16: 650 | T16: 650 | U16: 650 | V16: 650 | W16: 650 | Y16: 650 | AA16: =V16 -> 650 | AB16: =AA16 -> 650 | AC16: =AB16 -> 650
A17: =Factors!B19 -> BioFue | B17: 0 | C17: 0 | D17: 0 | E17: 0 | F17: 0 | G17: 0 | H17: 0 | I17: 0 | J17: 0 | K17: 0 | L17: 0 | M17: 0 | N17: 0 | O17: 0 | P17: 0 | Q17: 0 | R17: 0 | S17: 0 | T17: 0 | U17: 0 | V17: 0 | W17: 0 | Y17: 0 | AA17: =V17 -> 0 | AB17: =AA17 -> 0 | AC17: =AB17 -> 0
A18: =Factors!B20 -> PuChem | B18: =[2]IIASA2SweFor!$B$17 -> 5671.6872 | C18: =(B18+D18)/2 -> 6044.5608 | D18: =[2]IIASA2SweFor!$C$17 -> 6417.4344 | E18: =(D18+F18)/2 -> 6434.7604 | F18: =[2]IIASA2SweFor!$D$17 -> 6452.0865 | G18: =(F18+H18)/2 -> 6350.0742 | H18: =[2]IIASA2SweFor!$E$17 -> 6248.0619 | I18: =(H18+J18)/2 -> 6270.7509 | J18: =[2]IIASA2SweFor!$F$17 -> 6293.44 | K18: =(J18+L18)/2 -> 6375.9677 | L18: =[2]IIASA2SweFor!$G$17 -> 6458.4955 | M18: =(L18+N18)/2 -> 6444.1178 | N18: =[2]IIASA2SweFor!$H$17 -> 6429.7401 | O18: =(N18+P18)/2 -> 6331.6335 | P18: =[2]IIASA2SweFor!$I$17 -> 6233.5268 | Q18: =(P18+R18)/2 -> 6234.7922 | R18: =[2]IIASA2SweFor!$J$17 -> 6236.0576 | S18: =R18 -> 6236.0576 | T18: =S18 -> 6236.0576 | U18: =T18 -> 6236.0576 | V18: =U18 -> 6236.0576 | W18: =V18 -> 6236.0576 | Y18: =W18 -> 6236.0576 | AA18: =V18 -> 6236.0576 | AB18: =AA18 -> 6236.0576 | AC18: =AB18 -> 6236.0576
A19: =Factors!B21 -> PuMech | B19: =[2]IIASA2SweFor!$B$18 -> 4521.8223 | C19: =(B19+D19)/2 -> 4883.6396 | D19: =[2]IIASA2SweFor!$C$18 -> 5245.4569 | E19: =(D19+F19)/2 -> 5259.6188 | F19: =[2]IIASA2SweFor!$D$18 -> 5273.7806 | G19: =(F19+H19)/2 -> 5190.3982 | H19: =[2]IIASA2SweFor!$E$18 -> 5107.0159 | I19: =(H19+J19)/2 -> 5125.5613 | J19: =[2]IIASA2SweFor!$F$18 -> 5144.1068 | K19: =(J19+L19)/2 -> 5211.563 | L19: =[2]IIASA2SweFor!$G$18 -> 5279.0192 | M19: =(L19+N19)/2 -> 5267.2673 | N19: =[2]IIASA2SweFor!$H$18 -> 5255.5153 | O19: =(N19+P19)/2 -> 5175.3253 | P19: =[2]IIASA2SweFor!$I$18 -> 5095.1352 | Q19: =(P19+R19)/2 -> 5096.1695 | R19: =[2]IIASA2SweFor!$J$18 -> 5097.2038 | S19: =R19 -> 5097.2038 | T19: =S19 -> 5097.2038 | U19: =T19 -> 5097.2038 | V19: =U19 -> 5097.2038 | W19: =V19 -> 5097.2038 | Y19: =W19 -> 5097.2038 | AA19: =V19 -> 5097.2038 | AB19: =AA19 -> 5097.2038 | AC19: =AB19 -> 5097.2038
A20: =Factors!B22 -> PuDiss | B20: =[2]IIASA2SweFor!J$8 -> 7543.8623 | C20: =[2]IIASA2SweFor!K$8 -> 7543.8623 | D20: =[2]IIASA2SweFor!L$8 -> 7543.8623 | E20: =[2]IIASA2SweFor!M$8 -> 7543.8623 | F20: =[2]IIASA2SweFor!N$8 -> 7543.8623 | G20: =[2]IIASA2SweFor!O$8 -> 7543.8623 | H20: =[2]IIASA2SweFor!P$8 -> 7543.8623 | I20: =[2]IIASA2SweFor!Q$8 -> 7543.8623 | ... V20: =[2]IIASA2SweFor!AD$8 -> 7543.8623 | W20: =V20 -> 7543.8623 | Y20: =W20 -> 7543.8623 | AA20: =V20 -> 7543.8623 | AB20: =AA20 -> 7543.8623 | AC20: =AB20 -> 7543.8623
A21: =Factors!B23 -> PaChem | B21: =[2]IIASA2SweFor!$B$20 -> 7987.3416 | C21: =(B21+D21)/2 -> 7777.7666 | D21: =[2]IIASA2SweFor!$C$20 -> 7568.1915 | E21: =(D21+F21)/2 -> 7570.653 | F21: =[2]IIASA2SweFor!$D$20 -> 7573.1145 | G21: =(F21+H21)/2 -> 7604.3067 | H21: =[2]IIASA2SweFor!$E$20 -> 7635.4989 | I21: =(H21+J21)/2 -> 7696.5198 | J21: =[2]IIASA2SweFor!$F$20 -> 7757.5407 | K21: =(J21+L21)/2 -> 7827.7319 | L21: =[2]IIASA2SweFor!$G$20 -> 7897.9231 | M21: =(L21+N21)/2 -> 7883.9765 | N21: =[2]IIASA2SweFor!$H$20 -> 7870.0299 | O21: =(N21+P21)/2 -> 7790.4232 | P21: =[2]IIASA2SweFor!$I$20 -> 7710.8165 | Q21: =(P21+R21)/2 -> 7733.4272 | R21: =[2]IIASA2SweFor!$J$20 -> 7756.0378 | S21: =R21 -> 7756.0378 | T21: =S21 -> 7756.0378 | U21: =T21 -> 7756.0378 | V21: =U21 -> 7756.0378 | W21: =V21 -> 7756.0378 | Y21: =W21 -> 7756.0378 | AA21: =V21 -> 7756.0378 | AB21: =AA21 -> 7756.0378 | AC21: =AB21 -> 7756.0378
A22: =Factors!B24 -> OtChem | B22: =[2]IIASA2SweFor!$B$21 -> 8979.0978 | C22: =(B22+D22)/2 -> 8170.0116 | D22: =[2]IIASA2SweFor!$C$21 -> 7360.9254 | E22: =(D22+F22)/2 -> 7390.6459 | F22: =[2]IIASA2SweFor!$D$21 -> 7420.3664 | G22: =(F22+H22)/2 -> 7424.8682 | H22: =[2]IIASA2SweFor!$E$21 -> 7429.37 | I22: =(H22+J22)/2 -> 7433.1005 | J22: =[2]IIASA2SweFor!$F$21 -> 7436.831 | K22: =(J22+L22)/2 -> 7466.009 | L22: =[2]IIASA2SweFor!$G$21 -> 7495.1869 | M22: =(L22+N22)/2 -> 7417.2179 | N22: =[2]IIASA2SweFor!$H$21 -> 7339.2488 | O22: =(N22+P22)/2 -> 7233.4622 | P22: =[2]IIASA2SweFor!$I$21 -> 7127.6757 | Q22: =(P22+R22)/2 -> 7128.4762 | R22: =[2]IIASA2SweFor!$J$21 -> 7129.2767 | S22: =R22 -> 7129.2767 | T22: =S22 -> 7129.2767 | U22: =T22 -> 7129.2767 | V22: =U22 -> 7129.2767 | W22: =V22 -> 7129.2767 | Y22: =W22 -> 7129.2767 | AA22: =V22 -> 7129.2767 | AB22: =AA22 -> 7129.2767 | AC22: =AB22 -> 7129.2767
A23: =Factors!B25 -> OtMech | B23: =[2]IIASA2SweFor!$B$22 -> 6194.7449 | C23: =(B23+D23)/2 -> 5929.9977 | D23: =[2]IIASA2SweFor!$C$22 -> 5665.2505 | E23: =(D23+F23)/2 -> 5682.3231 | F23: =[2]IIASA2SweFor!$D$22 -> 5699.3956 | G23: =(F23+H23)/2 -> 5712.5328 | H23: =[2]IIASA2SweFor!$E$22 -> 5725.67 | I23: =(H23+J23)/2 -> 5770.158 | J23: =[2]IIASA2SweFor!$F$22 -> 5814.6461 | K23: =(J23+L23)/2 -> 5860.038 | L23: =[2]IIASA2SweFor!$G$22 -> 5905.4298 | M23: =(L23+N23)/2 -> 5897.5218 | N23: =[2]IIASA2SweFor!$H$22 -> 5889.6138 | O23: =(N23+P23)/2 -> 5835.6533 | P23: =[2]IIASA2SweFor!$I$22 -> 5781.6927 | Q23: =(P23+R23)/2 -> 5782.3887 | R23: =[2]IIASA2SweFor!$J$22 -> 5783.0846 | S23: =R23 -> 5783.0846 | T23: =S23 -> 5783.0846 | U23: =T23 -> 5783.0846 | V23: =U23 -> 5783.0846 | W23: =V23 -> 5783.0846 | Y23: =W23 -> 5783.0846 | AA23: =V23 -> 5783.0846 | AB23: =AA23 -> 5783.0846 | AC23: =AB23 -> 5783.0846
A24: =Factors!B26 -> NwMech | B24: =[2]IIASA2SweFor!$B$23 -> 5203.8885 | C24: =(B24+D24)/2 -> 4496.3514 | D24: =[2]IIASA2SweFor!$C$23 -> 3788.8144 | E24: =(D24+F24)/2 -> 3791.2725 | F24: =[2]IIASA2SweFor!$D$23 -> 3793.7307 | G24: =(F24+H24)/2 -> 3822.0282 | H24: =[2]IIASA2SweFor!$E$23 -> 3850.3257 | I24: =(H24+J24)/2 -> 3864.0911 | J24: =[2]IIASA2SweFor!$F$23 -> 3877.8565 | K24: =(J24+L24)/2 -> 3858.9236 | L24: =[2]IIASA2SweFor!$G$23 -> 3839.9906 | M24: =(L24+N24)/2 -> 3819.6774 | N24: =[2]IIASA2SweFor!$H$23 -> 3799.3642 | O24: =(N24+P24)/2 -> 3754.1684 | P24: =[2]IIASA2SweFor!$I$23 -> 3708.9727 | Q24: =(P24+R24)/2 -> 3709.5557 | R24: =[2]IIASA2SweFor!$J$23 -> 3710.1386 | S24: =R24 -> 3710.1386 | T24: =S24 -> 3710.1386 | U24: =T24 -> 3710.1386 | V24: =U24 -> 3710.1386 | W24: =V24 -> 3710.1386 | Y24: =W24 -> 3710.1386 | AA24: =V24 -> 3710.1386 | AB24: =AA24 -> 3710.1386 | AC24: =AB24 -> 3710.1386
A25: ParBoa | B25: 1738 | C25: 1738 | D25: 1738 | E25: 1738 | F25: 1738 | G25: 1738 | H25: 1738 | I25: 1738 | J25: 1738 | K25: 1738 | L25: 1738 | M25: 1738 | N25: 1738 | O25: 1738 | P25: 1738 | Q25: 1738 | R25: 1738 | S25: 1738 | T25: 1738 | U25: 1738 | V25: 1738 | W25: 1738
A27: Quantity for demand function (elasticity < 0)
A28: =Factors!B2 -> PinTim | B28: 0 | C28: =B28 -> 0 | D28: =C28 -> 0 | E28: =D28 -> 0 | F28: =E28 -> 0 | G28: =F28 -> 0 | H28: =G28 -> 0 | I28: =H28 -> 0 | J28: =I28 -> 0 | ... W28: =V28 -> 0 | Y28: =W28 -> 0 | AA28: =V28 -> 0 | AB28: =AA28 -> 0 | AC28: =AB28 -> 0
A29: =Factors!B3 -> PinPuw | B29: 0 | C29: =B29 -> 0 | D29: =C29 -> 0 | E29: =D29 -> 0 | F29: =E29 -> 0 | G29: =F29 -> 0 | H29: =G29 -> 0 | I29: =H29 -> 0 | J29: =I29 -> 0 | ... W29: =V29 -> 0 | Y29: =W29 -> 0 | AA29: =V29 -> 0 | AB29: =AA29 -> 0 | AC29: =AB29 -> 0
A30: =Factors!B4 -> SprTim | B30: 0 | C30: =B30 -> 0 | D30: =C30 -> 0 | E30: =D30 -> 0 | F30: =E30 -> 0 | G30: =F30 -> 0 | H30: =G30 -> 0 | I30: =H30 -> 0 | J30: =I30 -> 0 | ... W30: =V30 -> 0 | Y30: =W30 -> 0 | AA30: =V30 -> 0 | AB30: =AA30 -> 0 | AC30: =AB30 -> 0
A31: =Factors!B5 -> SprPuw | B31: 0 | C31: =B31 -> 0 | D31: =C31 -> 0 | E31: =D31 -> 0 | F31: =E31 -> 0 | G31: =F31 -> 0 | H31: =G31 -> 0 | I31: =H31 -> 0 | J31: =I31 -> 0 | ... W31: =V31 -> 0 | Y31: =W31 -> 0 | AA31: =V31 -> 0 | AB31: =AA31 -> 0 | AC31: =AB31 -> 0
A32: =Factors!B7 -> Decids | B32: 0 | C32: =B32 -> 0 | D32: =C32 -> 0 | E32: =D32 -> 0 | F32: =E32 -> 0 | G32: =F32 -> 0 | H32: =G32 -> 0 | I32: =H32 -> 0 | J32: =I32 -> 0 | ... W32: =V32 -> 0 | Y32: =W32 -> 0 | AA32: =V32 -> 0 | AB32: =AA32 -> 0 | AC32: =AB32 -> 0
A33: =Factors!B8 -> Sawdst | B33: 0 | C33: =B33 -> 0 | D33: =C33 -> 0 | E33: =D33 -> 0 | F33: =E33 -> 0 | G33: =F33 -> 0 | H33: =G33 -> 0 | I33: =H33 -> 0 | J33: =I33 -> 0 | ... W33: =V33 -> 0 | Y33: =W33 -> 0 | AA33: =V33 -> 0 | AB33: =AA33 -> 0 | AC33: =AB33 -> 0
A34: =Factors!B9 -> Chips_ | B34: 0 | C34: =B34 -> 0 | D34: =C34 -> 0 | E34: =D34 -> 0 | F34: =E34 -> 0 | G34: =F34 -> 0 | H34: =G34 -> 0 | I34: =H34 -> 0 | J34: =I34 -> 0 | ... W34: =V34 -> 0 | Y34: =W34 -> 0 | AA34: =V34 -> 0 | AB34: =AA34 -> 0 | AC34: =AB34 -> 0
A35: =Factors!B10 -> ResStm | B35: 0 | C35: 0 | D35: 0 | E35: 0 | F35: 0 | G35: 0 | H35: 0 | I35: 0 | J35: 0 | K35: 0 | L35: 0 | M35: 0 | N35: 0 | O35: 0 | P35: 0 | Q35: 0 | R35: 0 | S35: 0 | T35: 0 | U35: 0 | V35: 0 | W35: 0 | Y35: 0 | AA35: 0 | AB35: 0 | AC35: 0
A36: =Factors!B11 -> ResRot | B36: 0 | C36: 0 | D36: 0 | E36: 0 | F36: 0 | G36: 0 | H36: 0 | I36: 0 | J36: 0 | K36: 0 | L36: 0 | M36: 0 | N36: 0 | O36: 0 | P36: 0 | Q36: 0 | R36: 0 | S36: 0 | T36: 0 | U36: 0 | V36: 0 | W36: 0 | Y36: 0 | AA36: 0 | AB36: 0 | AC36: 0
A37: =Factors!B15 -> Sawnco | B37: 18628757 | C37: 18926066 | D37: 19223376 | E37: 19784190 | F37: 20345004 | G37: 20868631 | H37: 21392257 | I37: 21522292 | J37: 21652326 | K37: 21652326 | L37: 21652326 | M37: 21652326 | N37: 21652326 | O37: 21652326 | P37: 21652326 | Q37: 21652326 | R37: 21652326 | S37: 21652326 | T37: 21652326 | U37: 21652326 | V37: 21652326 | W37: 21652326 | X37: 18628757 | Y37: 18628757 | AA37: 19580317 | AB37: 19580317 | AC37: 19580317
A38: =Factors!B16 -> Sawnbe | B38: 0 | C38: 0 | D38: 0 | E38: 0 | F38: 0 | G38: 0 | H38: 0 | I38: 0 | J38: 0 | K38: 0 | L38: 0 | M38: 0 | N38: 0 | O38: 0 | P38: 0 | Q38: 0 | R38: 0 | S38: 0 | T38: 0 | U38: 0 | V38: 0 | W38: 0
A39: =Factors!B17 -> Heat__ | B39: 20250000 | C39: 20250000 | D39: 18000000 | E39: 18750000 | F39: 18000000 | G39: 18750000 | H39: 17250000 | I39: 17250000 | J39: 17250000 | K39: 17250000 | L39: 17250000 | M39: 17250000 | N39: 17250000 | O39: 17250000 | P39: 17250000 | Q39: 17250000 | R39: 17250000 | S39: 17250000 | T39: 17250000 | U39: 17250000 | V39: 17250000 | W39: 17250000 | Y39: 17250000 | AA39: 17250000 | AB39: 17250000 | AC39: 17250000
A40: =Factors!B18 -> Electr | B40: 0 | C40: 0 | D40: 0 | E40: 0 | F40: 0 | G40: 0 | H40: 0 | I40: 0 | J40: 0 | K40: 0 | L40: 0 | M40: 0 | N40: 0 | O40: 0 | P40: 0 | Q40: 0 | R40: 0 | S40: 0 | T40: 0 | U40: 0 | V40: 0 | W40: 0 | Y40: 0 | AA40: 0 | AB40: 0 | AC40: 0
A41: =Factors!B19 -> BioFue | B41: 0 | C41: 0 | D41: 0 | E41: 0 | F41: 0 | G41: 0 | H41: 0 | I41: 0 | J41: 0 | K41: 0 | L41: 0 | M41: 0 | N41: 0 | O41: 0 | P41: 0 | Q41: 0 | R41: 0 | S41: 0 | T41: 0 | U41: 0 | V41: 0 | W41: 0 | Y41: 0 | AA41: 0 | AB41: 0 | AC41: 0
A42: =Factors!B20 -> PuChem | B42: =1000000*[2]IIASA2SweFor!$B$26 -> 3404587.5 | C42: =(B42+D42)/2 -> 3419384.2 | D42: =1000000*[2]IIASA2SweFor!$C$26 -> 3434180.8 | E42: =(D42+F42)/2 -> 3473970.5 | F42: =1000000*[2]IIASA2SweFor!$D$26 -> 3513760.2 | G42: =(F42+H42)/2 -> 3530342.9 | H42: =1000000*[2]IIASA2SweFor!$E$26 -> 3546925.5 | I42: =(H42+J42)/2 -> 3569343.2 | J42: =1000000*[2]IIASA2SweFor!$F$26 -> 3591760.9 | K42: =(J42+L42)/2 -> 3618555.2 | L42: =1000000*[2]IIASA2SweFor!$G$26 -> 3645349.4 | M42: =(L42+N42)/2 -> 3672280.4 | N42: =1000000*[2]IIASA2SweFor!$H$26 -> 3699211.4 | O42: =(N42+P42)/2 -> 3725167.6 | P42: =1000000*[2]IIASA2SweFor!$I$26 -> 3751123.8 | Q42: =(P42+R42)/2 -> 3785468.4 | R42: =1000000*[2]IIASA2SweFor!$J$26 -> 3819813 | S42: =R42 -> 3819813 | T42: =S42 -> 3819813 | U42: =T42 -> 3819813 | V42: =U42 -> 3819813 | W42: =V42 -> 3819813 | Y42: =W42 -> 3819813 | AA42: 4081840.9 | AB42: 4081840.9 | AC42: 4081840.9
A43: =Factors!B21 -> PuMech | B43: =1000000*[2]IIASA2SweFor!$B$27 -> 530250 | C43: =(B43+D43)/2 -> 530250 | D43: =1000000*[2]IIASA2SweFor!$C$27 -> 530250 | E43: =(D43+F43)/2 -> 530250 | F43: =1000000*[2]IIASA2SweFor!$D$27 -> 530250 | G43: =(F43+H43)/2 -> 507175.95 | H43: =1000000*[2]IIASA2SweFor!$E$27 -> 484101.89 | I43: =(H43+J43)/2 -> 477912.14 | J43: =1000000*[2]IIASA2SweFor!$F$27 -> 471722.39 | K43: =(J43+L43)/2 -> 471722.39 | L43: =1000000*[2]IIASA2SweFor!$G$27 -> 471722.39 | M43: =(L43+N43)/2 -> 482982.65 | N43: =1000000*[2]IIASA2SweFor!$H$27 -> 494242.91 | O43: =(N43+P43)/2 -> 436559.85 | P43: =1000000*[2]IIASA2SweFor!$I$27 -> 378876.78 | Q43: =(P43+R43)/2 -> 365244.93 | R43: =1000000*[2]IIASA2SweFor!$J$27 -> 351613.08 | S43: =R43 -> 351613.08 | T43: =S43 -> 351613.08 | U43: =T43 -> 351613.08 | V43: =U43 -> 351613.08 | W43: =V43 -> 351613.08 | Y43: =W43 -> 351613.08 | AA43: 380726.74 | AB43: 380726.74 | AC43: 380726.74
A44: =Factors!B22 -> PuDiss | B44: =[2]IIASA2SweFor!J$9 -> 336337 | C44: =[2]IIASA2SweFor!K$9 -> 367970.03 | D44: =[2]IIASA2SweFor!L$9 -> 402578.19 | E44: =[2]IIASA2SweFor!M$9 -> 440441.31 | F44: =[2]IIASA2SweFor!N$9 -> 481865.51 | G44: =[2]IIASA2SweFor!O$9 -> 527185.73 | H44: =[2]IIASA2SweFor!P$9 -> 576768.38 | I44: =[2]IIASA2SweFor!Q$9 -> 631014.36 | ... V44: =[2]IIASA2SweFor!AD$9 -> 2030161.7 | W44: =V44 -> 2030161.7 | Y44: =W44 -> 2030161.7 | AA44: 417220.51 | AB44: 417220.51 | AC44: 417220.51
A45: =Factors!B23 -> PaChem | B45: =1000000*[2]IIASA2SweFor!$B$29 -> 5945000 | C45: =(B45+D45)/2 -> 5945000 | D45: =1000000*[2]IIASA2SweFor!$C$29 -> 5945000 | E45: =(D45+F45)/2 -> 5945000 | F45: =1000000*[2]IIASA2SweFor!$D$29 -> 5945000 | G45: =(F45+H45)/2 -> 5945000 | H45: =1000000*[2]IIASA2SweFor!$E$29 -> 5945000 | I45: =(H45+J45)/2 -> 5945000 | J45: =1000000*[2]IIASA2SweFor!$F$29 -> 5945000 | K45: =(J45+L45)/2 -> 5945000 | L45: =1000000*[2]IIASA2SweFor!$G$29 -> 5945000 | M45: =(L45+N45)/2 -> 5945000 | N45: =1000000*[2]IIASA2SweFor!$H$29 -> 5945000 | O45: =(N45+P45)/2 -> 5945000 | P45: =1000000*[2]IIASA2SweFor!$I$29 -> 5945000 | Q45: =(P45+R45)/2 -> 5945000 | R45: =1000000*[2]IIASA2SweFor!$J$29 -> 5945000 | S45: =R45 -> 5945000 | T45: =S45 -> 5945000 | U45: =T45 -> 5945000 | V45: =U45 -> 5945000 | W45: =V45 -> 5945000 | Y45: =W45 -> 5945000 | AA45: 7891956.3 | AB45: 7891956.3 | AC45: 7891956.3
A46: =Factors!B24 -> OtChem | B46: =1000000*[2]IIASA2SweFor!$B$30 -> 591250 | C46: =(B46+D46)/2 -> 591250 | D46: =1000000*[2]IIASA2SweFor!$C$30 -> 591250 | E46: =(D46+F46)/2 -> 591250 | F46: =1000000*[2]IIASA2SweFor!$D$30 -> 591250 | G46: =(F46+H46)/2 -> 591250 | H46: =1000000*[2]IIASA2SweFor!$E$30 -> 591250 | I46: =(H46+J46)/2 -> 591250 | J46: =1000000*[2]IIASA2SweFor!$F$30 -> 591250 | K46: =(J46+L46)/2 -> 591250 | L46: =1000000*[2]IIASA2SweFor!$G$30 -> 591250 | M46: =(L46+N46)/2 -> 591250 | N46: =1000000*[2]IIASA2SweFor!$H$30 -> 591250 | O46: =(N46+P46)/2 -> 588485.69 | P46: =1000000*[2]IIASA2SweFor!$I$30 -> 585721.38 | Q46: =(P46+R46)/2 -> 564168.59 | R46: =1000000*[2]IIASA2SweFor!$J$30 -> 542615.81 | S46: =R46 -> 542615.81 | T46: =S46 -> 542615.81 | U46: =T46 -> 542615.81 | V46: =U46 -> 542615.81 | W46: =V46 -> 542615.81 | Y46: =W46 -> 542615.81 | AA46: 574181.38 | AB46: 574181.38 | AC46: 574181.38
A47: =Factors!B25 -> OtMech | B47: =1000000*[2]IIASA2SweFor!$B$31 -> 1773750 | C47: =(B47+D47)/2 -> 1773750 | D47: =1000000*[2]IIASA2SweFor!$C$31 -> 1773750 | E47: =(D47+F47)/2 -> 1773750 | F47: =1000000*[2]IIASA2SweFor!$D$31 -> 1773750 | G47: =(F47+H47)/2 -> 1773750 | H47: =1000000*[2]IIASA2SweFor!$E$31 -> 1773750 | I47: =(H47+J47)/2 -> 1773750 | J47: =1000000*[2]IIASA2SweFor!$F$31 -> 1773750 | K47: =(J47+L47)/2 -> 1773750 | L47: =1000000*[2]IIASA2SweFor!$G$31 -> 1773750 | M47: =(L47+N47)/2 -> 1773750 | N47: =1000000*[2]IIASA2SweFor!$H$31 -> 1773750 | O47: =(N47+P47)/2 -> 1765457.1 | P47: =1000000*[2]IIASA2SweFor!$I$31 -> 1757164.1 | Q47: =(P47+R47)/2 -> 1692505.8 | R47: =1000000*[2]IIASA2SweFor!$J$31 -> 1627847.4 | S47: =R47 -> 1627847.4 | T47: =S47 -> 1627847.4 | U47: =T47 -> 1627847.4 | V47: =U47 -> 1627847.4 | W47: =V47 -> 1627847.4 | Y47: =W47 -> 1627847.4 | AA47: 1274484.7 | AB47: 1274484.7 | AC47: 1274484.7
A48: =Factors!B26 -> NwMech | B48: =1000000*[2]IIASA2SweFor!$B$32 -> 889000 | C48: =(B48+D48)/2 -> 889000 | D48: =1000000*[2]IIASA2SweFor!$C$32 -> 889000 | E48: =(D48+F48)/2 -> 889000 | F48: =1000000*[2]IIASA2SweFor!$D$32 -> 889000 | G48: =(F48+H48)/2 -> 889000 | H48: =1000000*[2]IIASA2SweFor!$E$32 -> 889000 | I48: =(H48+J48)/2 -> 889000 | J48: =1000000*[2]IIASA2SweFor!$F$32 -> 889000 | K48: =(J48+L48)/2 -> 889000 | L48: =1000000*[2]IIASA2SweFor!$G$32 -> 889000 | M48: =(L48+N48)/2 -> 877739.74 | N48: =1000000*[2]IIASA2SweFor!$H$32 -> 866479.47 | O48: =(N48+P48)/2 -> 844025.1 | P48: =1000000*[2]IIASA2SweFor!$I$32 -> 821570.73 | Q48: =(P48+R48)/2 -> 801972.42 | R48: =1000000*[2]IIASA2SweFor!$J$32 -> 782374.12 | S48: =R48 -> 782374.12 | T48: =S48 -> 782374.12 | U48: =T48 -> 782374.12 | V48: =U48 -> 782374.12 | W48: =V48 -> 782374.12 | Y48: =W48 -> 782374.12 | AA48: 765929.63 | AB48: 765929.63 | AC48: 765929.63
A49: ParBoa | B49: 1164002 | C49: 1204012 | D49: 1281462 | E49: 1340152 | F49: 1393776 | G49: 1448264 | H49: 1500856 | I49: 1500856 | J49: 1500856 | K49: 1500856 | L49: 1500856 | M49: 1500856 | N49: 1500856 | O49: 1500856 | P49: 1500856 | Q49: 1500856 | R49: 1500856 | S49: 1500856 | T49: 1500856 | U49: 1500856 | V49: 1500856 | W49: 1500856
A51: ImportPrices
A52: =Factors!B2 -> PinTim | B52: 0 | C52: 0 | D52: 0 | E52: 0 | F52: 0 | G52: 0 | H52: 0 | I52: 0 | J52: 0 | K52: 0 | L52: 0 | M52: 0 | N52: 0 | O52: 0 | P52: 0 | Q52: 0 | R52: 0 | S52: 0 | T52: 0 | U52: 0 | V52: 0 | W52: 0 | Y52: =Y$13/6 -> 358.59912 | AA52: 1 | AB52: 1 | AC52: 1
A53: =Factors!B3 -> PinPuw | B53: 0 | C53: 0 | D53: 0 | E53: 0 | F53: 0 | G53: 0 | H53: 0 | I53: 0 | J53: 0 | K53: 0 | L53: 0 | M53: 0 | N53: 0 | O53: 0 | P53: 0 | Q53: 0 | R53: 0 | S53: 0 | T53: 0 | U53: 0 | V53: 0 | W53: 0 | Y53: =Y$13/6 -> 358.59912 | AA53: 1 | AB53: 1 | AC53: 1
A54: =Factors!B4 -> SprTim | B54: 0 | C54: 0 | D54: 0 | E54: 0 | F54: 0 | G54: 0 | H54: 0 | I54: 0 | J54: 0 | K54: 0 | L54: 0 | M54: 0 | N54: 0 | O54: 0 | P54: 0 | Q54: 0 | R54: 0 | S54: 0 | T54: 0 | U54: 0 | V54: 0 | W54: 0 | Y54: =Y$13/6 -> 358.59912 | AA54: 1 | AB54: 1 | AC54: 1
A55: =Factors!B5 -> SprPuw | B55: 0 | C55: 0 | D55: 0 | E55: 0 | F55: 0 | G55: 0 | H55: 0 | I55: 0 | J55: 0 | K55: 0 | L55: 0 | M55: 0 | N55: 0 | O55: 0 | P55: 0 | Q55: 0 | R55: 0 | S55: 0 | T55: 0 | U55: 0 | V55: 0 | W55: 0 | Y55: =Y$13/6 -> 358.59912 | AA55: 1 | AB55: 1 | AC55: 1
A56: =Factors!B7 -> Decids | B56: 0 | C56: 0 | D56: 0 | E56: 0 | F56: 0 | G56: 0 | H56: 0 | I56: 0 | J56: 0 | K56: 0 | L56: 0 | M56: 0 | N56: 0 | O56: 0 | P56: 0 | Q56: 0 | R56: 0 | S56: 0 | T56: 0 | U56: 0 | V56: 0 | W56: 0 | Y56: =Y$13/6 -> 358.59912 | AA56: 1 | AB56: 1 | AC56: 1
A57: =Factors!B8 -> Sawdst | B57: =B9 -> 0 | C57: =C9 -> 0 | D57: =D9 -> 0 | E57: =E9 -> 0 | F57: =F9 -> 0 | G57: =G9 -> 0 | H57: =H9 -> 0 | I57: =I9 -> 0 | ... W57: =W9 -> 0 | Y57: =Y9 -> 0 | AA57: =AA9 -> 0 | AB57: =AB9 -> 0 | AC57: =AC9 -> 0
A58: =Factors!B9 -> Chips_ | B58: =B10 -> 0 | C58: =C10 -> 0 | D58: =D10 -> 0 | E58: =E10 -> 0 | F58: =F10 -> 0 | G58: =G10 -> 0 | H58: =H10 -> 0 | I58: =I10 -> 0 | ... W58: =W10 -> 0 | Y58: =Y10 -> 0 | AA58: =AA10 -> 0 | AB58: =AB10 -> 0 | AC58: =AC10 -> 0
A59: =Factors!B10 -> ResStm | B59: =B11 -> 0 | C59: =C11 -> 0 | D59: =D11 -> 0 | E59: =E11 -> 0 | F59: =F11 -> 0 | G59: =G11 -> 0 | H59: =H11 -> 0 | I59: =I11 -> 0 | ... W59: =W11 -> 0 | Y59: =Y11 -> 0 | AA59: =AA15*ConvFact!$A$1*2 -> 0 | AB59: =AB15*ConvFact!$A$1*2 -> 0 | AC59: =AC15*ConvFact!$A$1*2 -> 0
A60: =Factors!B11 -> ResRot | B60: 0 | C60: 0 | D60: 0 | E60: 0 | F60: 0 | G60: 0 | H60: 0 | I60: 0 | J60: 0 | K60: 0 | L60: 0 | M60: 0 | N60: 0 | O60: 0 | P60: 0 | Q60: 0 | R60: 0 | S60: 0 | T60: 0 | U60: 0 | V60: 0 | W60: 0 | Y60: 0 | AA60: 0 | AB60: 0 | AC60: 0
A61: =Factors!B15 -> Sawnco | B61: 0 | C61: 0 | D61: 0 | E61: 0 | F61: 0 | G61: 0 | H61: 0 | I61: 0 | J61: 0 | K61: 0 | L61: 0 | M61: 0 | N61: 0 | O61: 0 | P61: 0 | Q61: 0 | R61: 0 | S61: 0 | T61: 0 | U61: 0 | V61: 0 | W61: 0 | Y61: 0 | AA61: 0 | AB61: 0 | AC61: 0
A62: =Factors!B16 -> Sawnbe | B62: 0 | C62: 0 | D62: 0 | E62: 0 | F62: 0 | G62: 0 | H62: 0 | I62: 0 | J62: 0 | K62: 0 | L62: 0 | M62: 0 | N62: 0 | O62: 0 | P62: 0 | Q62: 0 | R62: 0 | S62: 0 | T62: 0 | U62: 0 | V62: 0 | W62: 0
A63: =Factors!B17 -> Heat__ | B63: 0 | C63: 0 | D63: 0 | E63: 0 | F63: 0 | G63: 0 | H63: 0 | I63: 0 | J63: 0 | K63: 0 | L63: 0 | M63: 0 | N63: 0 | O63: 0 | P63: 0 | Q63: 0 | R63: 0 | S63: 0 | T63: 0 | U63: 0 | V63: 0 | W63: 0 | Y63: 0 | AA63: 0 | AB63: 0 | AC63: 0
A64: =Factors!B18 -> Electr | B64: 0 | C64: 0 | D64: 0 | E64: 0 | F64: 0 | G64: 0 | H64: 0 | I64: 0 | J64: 0 | K64: 0 | L64: 0 | M64: 0 | N64: 0 | O64: 0 | P64: 0 | Q64: 0 | R64: 0 | S64: 0 | T64: 0 | U64: 0 | V64: 0 | W64: 0 | Y64: 0 | AA64: 0 | AB64: 0 | AC64: 0
A65: =Factors!B19 -> BioFue | B65: 0 | C65: 0 | D65: 0 | E65: 0 | F65: 0 | G65: 0 | H65: 0 | I65: 0 | J65: 0 | K65: 0 | L65: 0 | M65: 0 | N65: 0 | O65: 0 | P65: 0 | Q65: 0 | R65: 0 | S65: 0 | T65: 0 | U65: 0 | V65: 0 | W65: 0 | Y65: 0 | AA65: 0 | AB65: 0 | AC65: 0
A66: =Factors!B20 -> PuChem | B66: 0 | C66: 0 | D66: 0 | E66: 0 | F66: 0 | G66: 0 | H66: 0 | I66: 0 | J66: 0 | K66: 0 | L66: 0 | M66: 0 | N66: 0 | O66: 0 | P66: 0 | Q66: 0 | R66: 0 | S66: 0 | T66: 0 | U66: 0 | V66: 0 | W66: 0 | Y66: 0 | AA66: 0 | AB66: 0 | AC66: 0
A67: =Factors!B21 -> PuMech | B67: 0 | C67: 0 | D67: 0 | E67: 0 | F67: 0 | G67: 0 | H67: 0 | I67: 0 | J67: 0 | K67: 0 | L67: 0 | M67: 0 | N67: 0 | O67: 0 | P67: 0 | Q67: 0 | R67: 0 | S67: 0 | T67: 0 | U67: 0 | V67: 0 | W67: 0 | Y67: 0 | AA67: 0 | AB67: 0 | AC67: 0
A68: =Factors!B22 -> PuDiss | B68: 0 | C68: 0 | D68: 0 | E68: 0 | F68: 0 | G68: 0 | H68: 0 | I68: 0 | J68: 0 | K68: 0 | L68: 0 | M68: 0 | N68: 0 | O68: 0 | P68: 0 | Q68: 0 | R68: 0 | S68: 0 | T68: 0 | U68: 0 | V68: 0 | W68: 0 | Y68: 0 | AA68: 0 | AB68: 0 | AC68: 0
A69: =Factors!B23 -> PaChem | B69: 0 | C69: 0 | D69: 0 | E69: 0 | F69: 0 | G69: 0 | H69: 0 | I69: 0 | J69: 0 | K69: 0 | L69: 0 | M69: 0 | N69: 0 | O69: 0 | P69: 0 | Q69: 0 | R69: 0 | S69: 0 | T69: 0 | U69: 0 | V69: 0 | W69: 0 | Y69: 0 | AA69: 0 | AB69: 0 | AC69: 0
A70: =Factors!B24 -> OtChem | B70: 0 | C70: 0 | D70: 0 | E70: 0 | F70: 0 | G70: 0 | H70: 0 | I70: 0 | J70: 0 | K70: 0 | L70: 0 | M70: 0 | N70: 0 | O70: 0 | P70: 0 | Q70: 0 | R70: 0 | S70: 0 | T70: 0 | U70: 0 | V70: 0 | W70: 0 | Y70: 0 | AA70: 0 | AB70: 0 | AC70: 0
A71: =Factors!B25 -> OtMech | B71: 0 | C71: 0 | D71: 0 | E71: 0 | F71: 0 | G71: 0 | H71: 0 | I71: 0 | J71: 0 | K71: 0 | L71: 0 | M71: 0 | N71: 0 | O71: 0 | P71: 0 | Q71: 0 | R71: 0 | S71: 0 | T71: 0 | U71: 0 | V71: 0 | W71: 0 | Y71: 0 | AA71: 0 | AB71: 0 | AC71: 0
A72: =Factors!B26 -> NwMech | B72: 0 | C72: 0 | D72: 0 | E72: 0 | F72: 0 | G72: 0 | H72: 0 | I72: 0 | J72: 0 | K72: 0 | L72: 0 | M72: 0 | N72: 0 | O72: 0 | P72: 0 | Q72: 0 | R72: 0 | S72: 0 | T72: 0 | U72: 0 | V72: 0 | W72: 0 | Y72: 0 | AA72: 0 | AB72: 0 | AC72: 0
A74: MaxImports
A75: =Factors!B2 -> PinTim | B75: 400000 | C75: 400000 | D75: 400000 | E75: 400000 | F75: 400000 | G75: 400000 | H75: 400000 | I75: 400000 | J75: 400000 | K75: 400000 | L75: 400000 | M75: 400000 | N75: 400000 | O75: 400000 | P75: 400000 | Q75: 400000 | R75: 400000 | S75: 400000 | T75: 400000 | U75: 400000 | V75: 400000 | W75: 400000 | Y75: =W75*0.8 -> 320000 | AA75: =V75*0.8 -> 320000 | AB75: =AA75*0.8 -> 256000 | AC75: =AB75*0.8 -> 204800
A76: =Factors!B3 -> PinPuw | B76: 1300000 | C76: 1300000 | D76: 1300000 | E76: 1300000 | F76: 1300000 | G76: 1300000 | H76: 1300000 | I76: 1300000 | J76: 1300000 | K76: 1300000 | L76: 1300000 | M76: 1300000 | N76: 1300000 | O76: 1300000 | P76: 1300000 | Q76: 1300000 | R76: 1300000 | S76: 1300000 | T76: 1300000 | U76: 1300000 | V76: 1300000 | W76: 1300000 | Y76: =W76*0.8 -> 1040000 | AA76: =V76*0.8 -> 1040000 | AB76: =AA76*0.8 -> 832000 | AC76: =AB76*0.8 -> 665600
A77: =Factors!B4 -> SprTim | B77: 500000 | C77: 500000 | D77: 500000 | E77: 500000 | F77: 500000 | G77: 500000 | H77: 500000 | I77: 500000 | J77: 500000 | K77: 500000 | L77: 500000 | M77: 500000 | N77: 500000 | O77: 500000 | P77: 500000 | Q77: 500000 | R77: 500000 | S77: 500000 | T77: 500000 | U77: 500000 | V77: 500000 | W77: 500000 | Y77: =W77*0.8 -> 400000 | AA77: =V77*0.8 -> 400000 | AB77: =AA77*0.8 -> 320000 | AC77: =AB77*0.8 -> 256000
A78: =Factors!B5 -> SprPuw | B78: 1800000 | C78: 1800000 | D78: 1800000 | E78: 1800000 | F78: 1800000 | G78: 1800000 | H78: 1800000 | I78: 1800000 | J78: 1800000 | K78: 1800000 | L78: 1800000 | M78: 1800000 | N78: 1800000 | O78: 1800000 | P78: 1800000 | Q78: 1800000 | R78: 1800000 | S78: 1800000 | T78: 1800000 | U78: 1800000 | V78: 1800000 | W78: 1800000 | Y78: =W78*0.8 -> 1440000 | AA78: =V78*0.8 -> 1440000 | AB78: =AA78*0.8 -> 1152000 | AC78: =AB78*0.8 -> 921600
A79: =Factors!B7 -> Decids | B79: 2700000 | C79: 2700000 | D79: 2700000 | E79: 2700000 | F79: 2700000 | G79: 2700000 | H79: 2700000 | I79: 2700000 | J79: 2700000 | K79: 2700000 | L79: 2700000 | M79: 2700000 | N79: 2700000 | O79: 2700000 | P79: 2700000 | Q79: 2700000 | R79: 2700000 | S79: 2700000 | T79: 2700000 | U79: 2700000 | V79: 2700000 | W79: 2700000 | Y79: =W79*0.8 -> 2160000 | AA79: =V79*0.8 -> 2160000 | AB79: =AA79*0.8 -> 1728000 | AC79: =AB79*0.8 -> 1382400
A80: =Factors!B8 -> Sawdst | B80: 0 | C80: 0 | D80: 0 | E80: 0 | F80: 0 | G80: 0 | H80: 0 | I80: 0 | J80: 0 | K80: 0 | L80: 0 | M80: 0 | N80: 0 | O80: 0 | P80: 0 | Q80: 0 | R80: 0 | S80: 0 | T80: 0 | U80: 0 | V80: 0 | W80: 0 | Y80: 0 | AA80: 0 | AB80: 0 | AC80: 0
A81: =Factors!B9 -> Chips_ | B81: 0 | C81: 0 | D81: 0 | E81: 0 | F81: 0 | G81: 0 | H81: 0 | I81: 0 | J81: 0 | K81: 0 | L81: 0 | M81: 0 | N81: 0 | O81: 0 | P81: 0 | Q81: 0 | R81: 0 | S81: 0 | T81: 0 | U81: 0 | V81: 0 | W81: 0 | Y81: 0 | AA81: 0 | AB81: 0 | AC81: 0
A82: =Factors!B10 -> ResStm | B82: 0 | C82: 0 | D82: 0 | E82: 0 | F82: 0 | G82: 0 | H82: 0 | I82: 0 | J82: 0 | K82: 0 | L82: 0 | M82: 0 | N82: 0 | O82: 0 | P82: 0 | Q82: 0 | R82: 0 | S82: 0 | T82: 0 | U82: 0 | V82: 0 | W82: 0 | Y82: 0 | AA82: 100000000 | AB82: 100000000 | AC82: 100000000
A83: =Factors!B11 -> ResRot | B83: 0 | C83: 0 | D83: 0 | E83: 0 | F83: 0 | G83: 0 | H83: 0 | I83: 0 | J83: 0 | K83: 0 | L83: 0 | M83: 0 | N83: 0 | O83: 0 | P83: 0 | Q83: 0 | R83: 0 | S83: 0 | T83: 0 | U83: 0 | V83: 0 | W83: 0 | Y83: 0 | AA83: 0 | AB83: 0 | AC83: 0
A84: =Factors!B15 -> Sawnco | B84: 0 | C84: 0 | D84: 0 | E84: 0 | F84: 0 | G84: 0 | H84: 0 | I84: 0 | J84: 0 | K84: 0 | L84: 0 | M84: 0 | N84: 0 | O84: 0 | P84: 0 | Q84: 0 | R84: 0 | S84: 0 | T84: 0 | U84: 0 | V84: 0 | W84: 0 | Y84: 0 | AA84: 0 | AB84: 0 | AC84: 0
A85: =Factors!B16 -> Sawnbe | B85: 0 | C85: 0 | D85: 0 | E85: 0 | F85: 0 | G85: 0 | H85: 0 | I85: 0 | J85: 0 | K85: 0 | L85: 0 | M85: 0 | N85: 0 | O85: 0 | P85: 0 | Q85: 0 | R85: 0 | S85: 0 | T85: 0 | U85: 0 | V85: 0 | W85: 0
A86: =Factors!B17 -> Heat__ | B86: 0 | C86: 0 | D86: 0 | E86: 0 | F86: 0 | G86: 0 | H86: 0 | I86: 0 | J86: 0 | K86: 0 | L86: 0 | M86: 0 | N86: 0 | O86: 0 | P86: 0 | Q86: 0 | R86: 0 | S86: 0 | T86: 0 | U86: 0 | V86: 0 | W86: 0 | Y86: 0 | AA86: 0 | AB86: 0 | AC86: 0
A87: =Factors!B18 -> Electr | B87: 0 | C87: 0 | D87: 0 | E87: 0 | F87: 0 | G87: 0 | H87: 0 | I87: 0 | J87: 0 | K87: 0 | L87: 0 | M87: 0 | N87: 0 | O87: 0 | P87: 0 | Q87: 0 | R87: 0 | S87: 0 | T87: 0 | U87: 0 | V87: 0 | W87: 0 | Y87: 0 | AA87: 0 | AB87: 0 | AC87: 0
A88: =Factors!B19 -> BioFue | B88: 0 | C88: 0 | D88: 0 | E88: 0 | F88: 0 | G88: 0 | H88: 0 | I88: 0 | J88: 0 | K88: 0 | L88: 0 | M88: 0 | N88: 0 | O88: 0 | P88: 0 | Q88: 0 | R88: 0 | S88: 0 | T88: 0 | U88: 0 | V88: 0 | W88: 0 | Y88: 0 | AA88: 0 | AB88: 0 | AC88: 0
A89: =Factors!B20 -> PuChem | B89: 0 | C89: 0 | D89: 0 | E89: 0 | F89: 0 | G89: 0 | H89: 0 | I89: 0 | J89: 0 | K89: 0 | L89: 0 | M89: 0 | N89: 0 | O89: 0 | P89: 0 | Q89: 0 | R89: 0 | S89: 0 | T89: 0 | U89: 0 | V89: 0 | W89: 0 | Y89: 0 | AA89: 0 | AB89: 0 | AC89: 0
A90: =Factors!B21 -> PuMech | B90: 0 | C90: 0 | D90: 0 | E90: 0 | F90: 0 | G90: 0 | H90: 0 | I90: 0 | J90: 0 | K90: 0 | L90: 0 | M90: 0 | N90: 0 | O90: 0 | P90: 0 | Q90: 0 | R90: 0 | S90: 0 | T90: 0 | U90: 0 | V90: 0 | W90: 0 | Y90: 0 | AA90: 0 | AB90: 0 | AC90: 0
A91: =Factors!B22 -> PuDiss | B91: 0 | C91: 0 | D91: 0 | E91: 0 | F91: 0 | G91: 0 | H91: 0 | I91: 0 | J91: 0 | K91: 0 | L91: 0 | M91: 0 | N91: 0 | O91: 0 | P91: 0 | Q91: 0 | R91: 0 | S91: 0 | T91: 0 | U91: 0 | V91: 0 | W91: 0 | Y91: 0 | AA91: 0 | AB91: 0 | AC91: 0
A92: =Factors!B23 -> PaChem | B92: 0 | C92: 0 | D92: 0 | E92: 0 | F92: 0 | G92: 0 | H92: 0 | I92: 0 | J92: 0 | K92: 0 | L92: 0 | M92: 0 | N92: 0 | O92: 0 | P92: 0 | Q92: 0 | R92: 0 | S92: 0 | T92: 0 | U92: 0 | V92: 0 | W92: 0 | Y92: 0 | AA92: 0 | AB92: 0 | AC92: 0
A93: =Factors!B24 -> OtChem | B93: 0 | C93: 0 | D93: 0 | E93: 0 | F93: 0 | G93: 0 | H93: 0 | I93: 0 | J93: 0 | K93: 0 | L93: 0 | M93: 0 | N93: 0 | O93: 0 | P93: 0 | Q93: 0 | R93: 0 | S93: 0 | T93: 0 | U93: 0 | V93: 0 | W93: 0 | Y93: 0 | AA93: 0 | AB93: 0 | AC93: 0
A94: =Factors!B25 -> OtMech | B94: 0 | C94: 0 | D94: 0 | E94: 0 | F94: 0 | G94: 0 | H94: 0 | I94: 0 | J94: 0 | K94: 0 | L94: 0 | M94: 0 | N94: 0 | O94: 0 | P94: 0 | Q94: 0 | R94: 0 | S94: 0 | T94: 0 | U94: 0 | V94: 0 | W94: 0 | Y94: 0 | AA94: 0 | AB94: 0 | AC94: 0
A95: =Factors!B26 -> NwMech | B95: 0 | C95: 0 | D95: 0 | E95: 0 | F95: 0 | G95: 0 | H95: 0 | I95: 0 | J95: 0 | K95: 0 | L95: 0 | M95: 0 | N95: 0 | O95: 0 | P95: 0 | Q95: 0 | R95: 0 | S95: 0 | T95: 0 | U95: 0 | V95: 0 | W95: 0 | Y95: 0 | AA95: 0 | AB95: 0 | AC95: 0

Sheet ConvFact
A1: 4.9 | B1: MWhperTonTS | C1: Wood input
A2: 0.46 | B2: TonTSperM3fub | C2: Wood input
A3: =A1*A2 -> 2.254 | B3: MWhperM3fub | C3: Wood input
A4: 0.5 | B4: CperTS
A5: 0.95 | B5: HeatPlantEfficiency
A6: 1 | B6: CHPPlantEfficiency
A7: 0.64 | B7: HTLPlantEfficiency
A8: =[1]SawMill!$Y$19 -> 0.17797461 | B8: M3fubSawdustPerM3fub
A9: =[1]SawMill!$Y$18 -> 0.2545616 | B9: M3fubChipsM3fub
A10: =[1]SawMill!$Y$20 -> 0.48049868 | B10: M3svPerM3fub
A11: 0.21 | B11: TonSulphateSulphitePulpPerM3fub
A12: 0.21 | B12: TonDissolvingPulpPerM3fub
A13: 0.42 | B13: TonMechanicalPulpPerM3fub
A14: 0.43 | B14: TonHalfChemicalPulpPerM3fub
A15: 1.1 | B15: TonPaChemPerTonPu
A16: 1.3 | B16: TonOtChemPerTonPu
A17: 1.3 | B17: TonOtMechPerTonPu
A18: 1.1 | B18: TonNwMechPerTonPu
A19: 1.127 | B19: MWhPerTonPuChem | C19: Electricity output
A20: -2.45 | B20: MWhPerTonPuMech | C20: Electricity output
A21: -0.467 | B21: MWhPerTonPpChem | C21: Electricity output
A22: -0.907 | B22: MWhPerTonPuBCCS | C22: Electricity output
A23: -0.44 | B23: MWhPerTonPpBCCS | C23: Electricity output
A24: -0.021 | B24: MWhPerMWhBiofuel | C24: Electricity output
A25: =12/44 -> 0.27272727 | B25: CperCO2
A26: 0.67 | B26: M3fubParBoaPerM3fub
A27: -0.16405841 | B27: MWhperM3fubParBoa | C27: Electricity output
